Workbook

Sheet Requirements map
A1: Req ID | B1: Module | C1: Priority | D1: Requirement | E1: What we built | F1: Portal screen | G1: Workspace | H1: Code | I1: How a user reaches it | J1: Test cases | K1: Result | L1: Explanation / demo example
A2: G-1 | B2: CGF | C2: Mandatory | D2: The system shall provide a centralized, searchable repository of every committee and governance forum, holding forum details, charter documents and associated metadata. Access, visibility and permitted actions shall be governed by role-based access control. | E2: Governance Forum with DocPerm rows; /forums register and /forum detail over the permission-checked REST API; www/forum.py throws for a viewer without read access and offers Edit only with write permission. | F2: /forums /forum?name=… | G2: /app/governance-forum — Governance workspace | H2: consilium/www/forum.py (portal page) consilium/www/forums.py (portal page) consilium/governance/doctype/governance_forum/governance_forum.py (Governance Forum) consilium/governance/inventory.py (module under the cited tests) | I2: (a) Through a purpose-built portal screen | J2: governance.tests.test_entities.TestGovernanceEntities.* (all 19) governance.tests.test_inventory.TestSearchAndFilter.test_search_respects_permissions consilium_core.tests.test_portal_pages.TestReaderWithoutAccess.* (all 2) | K2: ✅ | L2: 14 forums, from FRM-2026-00001 Board of Directors down to working groups (FRM-2026-00013).
A3: G-2 | B3: CGF | C3: Mandatory | D3: The system shall provide advanced search and filtering of forums by any indexed metadata field. | E3: /forums filters by type, status, cadence, risk category, operating group and standing, plus the four multi-valued dimensions (inventory.inventory_filters, inventory.tagged_forum_names, intersecting). Free-text search over name, code and mandate, also taken from ?q=. The header's global search finds a forum by identifier or name from any page (consilium_core/search.py). Retired taxonomy values are marked, not offered as new. Paged server-side, with Export CSV. | F3: /forums | G3: /app/governance-forum — Governance workspace | H3: consilium/governance/inventory.py → inventory_filters() consilium/governance/inventory.py → tagged_forum_names() consilium/consilium_core/search.py consilium/www/forums.py (portal page) consilium/governance/doctype/governance_forum/governance_forum.py (Governance Forum) | I3: (a) Through a purpose-built portal screen | J3: governance.tests.test_inventory.TestSearchAndFilter.* (all 4) governance.tests.test_governance_gaps.TestInventoryReads.test_tagged_filters_intersect governance.tests.test_governance_gaps.TestInventoryReads.test_tagged_names_respect_permission governance.tests.test_governance_gaps.TestInventoryReads.test_filter_values_include_retired_ones_marked consilium_core.tests.test_global_search.TestGlobalSearch.* (all 9) | K3: ✅ | L3: /forums?standing=overdue lists FRM-2026-00008 Model Risk Committee (review due 2026-08-14).
A4: G-3 | B4: CGF | C4: Mandatory | D4: The system shall allow a forum to be tagged with controlled metadata drawn from standard taxonomies, with dependent-field behaviour and dropdown-controlled selection. Minimum attributes: forum identifier, name, type, description, meeting cadence, chair, primary risk category, legal entity, owning organisation (operating group) and owning organisation (line of business). | E4: Link fields plus four multi-select child tables (business unit, risk type, legal entity, jurisdiction). Operating-group and line-of-business validation. Captured in /create-forum and on desk; shown on /forum. Retired values are not offered (taxonomy standard_queries hook). | F4: /create-forum /forum?name=… | G4: /app/governance-forum — Governance workspace | H4: consilium/www/create_forum.py (portal page) consilium/www/forum.py (portal page) consilium/consilium_core/taxonomy.py (module under the cited tests) consilium/governance/doctype/governance_forum/governance_forum.py (Governance Forum) | I4: (a) Through a purpose-built portal screen | J4: governance.tests.test_entities.TestGovernanceEntities.test_four_dimensions_are_multi_valued_and_two_are_not governance.tests.test_entities.TestGovernanceEntities.test_the_owning_organisation_must_be_an_operating_group governance.tests.test_entities.TestGovernanceEntities.test_a_line_of_business_must_sit_under_its_operating_group consilium_core.tests.test_entities.TestTaxonomies.* (all 9) consilium_core.tests.test_taxonomy.TestActiveOnlySearch.* (all 6) | K4: ✅ | L4: FRM-2026-00007 Technology and Cyber Risk Committee: type MGMT_CTTE, regulatory-required, 2 business units and 3 risk types.
A5: G-4 | B5: CGF | C5: Mandatory | D5: The system shall allow a forum to be mapped to related forums (upstream and downstream), to be flagged as regulatory-required with dependent capture of the applicable regulatory requirements. | E5: parent_forum, Forum Link (upstream and downstream), and Forum Regulatory Requirement, required when the flag is set. inventory.interconnectivity is drawn as SVG on /forum (Linkages tab). Links are edited on desk. | F5: /forum?name=… | G5: /app/governance-forum → 'Forum Link' table /app/governance-forum → 'Forum Regulatory Requirement' table | H5: consilium/governance/inventory.py → interconnectivity() consilium/www/forum.py (portal page) | I5: (a) Through a purpose-built portal screen | J5: governance.tests.test_entities.TestGovernanceEntities.test_regulatory_detail_becomes_required_when_the_flag_is_set governance.tests.test_entities.TestGovernanceEntities.test_a_forum_cannot_be_its_own_ancestor governance.tests.test_entities.TestGovernanceEntities.test_a_link_takes_its_direction_from_the_field_it_sits_in governance.tests.test_entities.TestGovernanceEntities.test_a_forum_cannot_link_to_itself governance.tests.test_inventory.TestRelationships.* (all 2) | K5: ✅ | L5: 15 Forum Link rows. FRM-2026-00005 Executive Risk Committee answers to FRM-2026-00004 and FRM-2026-00002 and has five sub-committees. 7 regulatory-required forums, for example FRM-2026-00010 with 2 requirements.
A6: G-5 | B6: CGF | C6: Mandatory | D6: The system shall support the committee formation process: structured intake, evaluation against defined criteria, capture of approval evidence, exception handling and status tracking. Evaluation criteria: gap in risk or governance coverage; duplication with existing forums; clear escalation and reporting pathways; alignment with the risk management framework, risk taxonomy and policy structure; resource feasibility. Charter drafts must be reviewable by the Risk Governance Office for completeness and appropriateness before approval. Acceptable approval evidence includes email, meeting minutes and signed documents. Disputes and exceptions resolve through the Head of Risk Governance. | E6: Committee Formation Request + Formation Evaluation (5 criteria seeded) + formation.py. /create-forum → /formation-requests → /formation-request covers findings, return and respond, approval steps, exception to the designated authority, charter challenge, approve, reject and withdraw. Approval creates a draft forum. Gap: Charter Approval Evidence rows are captured on desk only (DK-1 is in the trace). | F6: /create-forum /formation-requests /formation-request?name=… | G6: /app/committee-formation-request — Governance workspace /app/committee-formation-request → 'Formation Evaluation' table /app/committee-charter → 'Charter Approval Evidence' table | H6: consilium/governance/formation.py consilium/www/create_forum.py (portal page) consilium/www/formation_requests.py (portal page) consilium/www/formation_request.py (portal page) consilium/governance/doctype/committee_formation_request/committee_formation_request.py (Committee Formation Request) | I6: (a) Through a purpose-built portal screen | J6: governance.tests.test_formation.* (all 27) governance.tests.test_formation_portal.* (all 35) | K6: ✅ | L6: One request at each stage: CFR-2026-00006 Draft; 00004 Under Evaluation; 00003 Returned To Originator; 00002 Pending Approval; 00005 Rejected; 00001 Approved → FRM-2026-00014 Data Governance Council, with bypass EXCA-00001.
A7: G-6 | B7: CGF | C7: Mandatory | D7: The system shall support administratively configurable automated workflows for establishing, maintaining and disbanding forums, including approvals and escalations, without custom development. | E7: Formation Approval Route (steps, sequence and mode as data); Workflow State Flag (130 rows); Watched Field Set; disbandment trigger scenarios and approver roles are select options. Nothing branches on a state label. All on desk. | F7: — (no portal screen) | G7: /app/formation-approval-route — Governance workspace /app/workflow-state-flag — Consilium Administration workspace /app/watched-field-set — Consilium Administration workspace | H7: consilium/governance/doctype/formation_approval_route/formation_approval_route.py (Formation Approval Route) consilium/consilium_core/doctype/workflow_state_flag/workflow_state_flag.py (Workflow State Flag) consilium/consilium_core/doctype/watched_field_set/watched_field_set.py (Watched Field Set) consilium/governance/formation.py (module under the cited tests) consilium/consilium_core/state_flags.py (module under the cited tests) consilium/governance/lifecycle.py (module under the cited tests) | I7: (b) Through the desk, configuration or a scheduled job — by design | J7: governance.tests.test_formation.TestApprovalRoute.test_the_steps_are_configuration governance.tests.test_formation.TestApprovalRoute.test_a_route_change_changes_the_steps_without_a_deployment consilium_core.tests.test_state_flags.TestStateFlags.* (all 7) governance.tests.test_lifecycle.TestStateFlags.* (all 3) governance.tests.test_lifecycle.TestWatchedFields.* (all 5) | K7: ✅ | L7: "Standard Formation Approval" route (request type Any). CFR-2026-00002 shows the three steps it raised.
A8: G-7 | B8: CGF | C8: Mandatory | D8: The system shall prevent progression of a formation request when required information, approvals or evidence are incomplete or inconsistent. It shall validate intake completeness, check the request against the existing forum inventory for overlap or conflict, allow review and challenge of the draft charter before the requester seeks final approval, and validate submitted approvals against the intake record and charter before the forum inventory is updated. | E8: formation.approval_blockers covers: unassessed criteria; completeness confirmation; undecided steps; refused steps not bypassed; and an uncleared charter challenge (charters.uncleared_challenges). The challenge is recorded on /formation-request (charters.record_charter_challenge). An open challenge also blocks a favourable compliance decision (lifecycle.refuse_standing_over_open_challenge). Gap: the charter's approval evidence (in charters.clearance_blockers) is shown on /forum but is not a formation approval blocker. | F8: /formation-request?name=… /forum?name=… | G8: /app/committee-formation-request — Governance workspace /app/committee-charter — Governance workspace /app/governance-forum — Governance workspace | H8: consilium/governance/formation.py → approval_blockers() consilium/governance/charters.py → uncleared_challenges() consilium/governance/charters.py → record_charter_challenge() consilium/governance/lifecycle.py → refuse_standing_over_open_challenge() consilium/governance/charters.py → clearance_blockers() consilium/www/formation_request.py (portal page) consilium/www/forum.py (portal page) consilium/governance/doctype/committee_formation_request/committee_formation_request.py (Committee Formation Request) consilium/governance/doctype/committee_charter/committee_charter.py (Committee Charter) consilium/governance/doctype/governance_forum/governance_forum.py (Governance Forum) | I8: (a) Through a purpose-built portal screen | J8: governance.tests.test_formation.TestIntake.test_submission_runs_the_overlap_check governance.tests.test_formation.TestEvaluation.* (all 4) governance.tests.test_governance_gaps.TestFormationCharterGate.* (all 2) governance.tests.test_governance_gaps.TestStandingGate.* (all 3) governance.tests.test_wave3_governance.TestCharterChallengeOnTheRequest.* (all 2) governance.tests.test_charters.TestEffectiveChallenge.* (all 4) | K8: ✅ | L8: CFR-2026-00002 is held by CHT-2026-00014 "Changes Requested" and by an open Delegating Authority step. CHT-2026-00007 (FRM-2026-00007) "Changes Requested".
A9: G-8 | B9: CGF | C9: Mandatory | D9: The system shall support a multi-step approval process across stakeholders and roles, with sequential or parallel approvals, capturing charter approval. Approval paths may differ by materiality of change and by forum type. | E9: Route steps become Core Approval Decisions. Sequential order is enforced in approvals.record_decision (waiting_on, is_turn). Parallel steps and peers sharing a sequence number do not wait. Role-based steps form a queue. Steps are decided on /formation-request by the assignee, a queue member or a delegate. A bypass needs an Exception Authorisation, waives only its own step, and cannot be made by the step's own holder. Missing: the path cannot differ by forum type or by materiality of change. formation.resolve_route selects only by request_type (Any, Create, Modify, Retire), and Formation Approval Route has no forum-type or materiality field. | F9: /formation-request?name=… | G9: /app/approval-decision — Consilium Administration workspace /app/exception-authorisation — Consilium Administration workspace /app/formation-approval-route — Governance workspace | H9: consilium/consilium_core/approvals.py → record_decision() consilium/consilium_core/approvals.py → waiting_on() consilium/consilium_core/approvals.py → is_turn() consilium/governance/formation.py → resolve_route() consilium/www/formation_request.py (portal page) consilium/consilium_core/doctype/approval_decision/approval_decision.py (Approval Decision) consilium/consilium_core/doctype/exception_authorisation/exception_authorisation.py (Exception Authorisation) consilium/governance/doctype/formation_approval_route/formation_approval_route.py (Formation Approval Route) | I9: (d) Not implemented, wholly or in a mandatory clause | J9: governance.tests.test_formation.TestApprovalRoute.* (all 5) governance.tests.test_formation_portal.TestApprovalThroughThePortal.* (all 5) consilium_core.tests.test_core_controls_wave3.TestSequentialApprovals.* (all 6) governance.tests.test_wave3_governance.TestFormationStepOrder.* (all 4) governance.tests.test_w3_guides.TestABypassWaivesOnlyItsOwnStep.* (all 1) governance.tests.test_w3_guides.TestNobodyBypassesTheirOwnStep.* (all 2) governance.tests.test_w3_guides.TestARoleIsAQueue.* (all 5) consilium_core.tests.test_services.TestApprovals.* (all 5) | K9: ✅ (not the path-selection clause) | L9: CFR-2026-00002: Risk Governance Office Evaluation (seq 1) approved, Sponsor Endorsement (seq 2) approved, Delegating Authority (seq 2) pending. CFR-2026-00001: Sponsor step bypassed under EXCA-00001.
A10: G-9 | B10: CGF | C10: Mandatory | D10: The system shall track every change to a forum, maintain complete history, and log every user action with a timestamp and attributed actor. Prior versions shall be archivable and viewable. The system shall additionally allow an authorised user to revert a forum record to a previous version. | E10: A revision.snapshot doc event on Governance Forum writes a version chain. /forum History tab offers a revision history with Revert (revision.history and revision.revert: reason required, governance office only; lifecycle and derived fields are never restored; reverting a watched field sends the forum back for review). Record history (evidence.record_history, now including notifications) and an evidence-pack ZIP with a SHA-256 manifest (evidence.export_pack). | F10: /forum?name=… | G10: /app/governance-forum — Governance workspace | H10: consilium/consilium_core/revision.py → snapshot() consilium/consilium_core/revision.py → history() consilium/consilium_core/revision.py → revert() consilium/consilium_core/evidence.py → record_history() consilium/consilium_core/evidence.py → export_pack() consilium/www/forum.py (portal page) consilium/governance/doctype/governance_forum/governance_forum.py (Governance Forum) consilium/consilium_core/versioning.py (module under the cited tests) | I10: (a) Through a purpose-built portal screen | J10: consilium_core.tests.test_revision.TestForumRevision.* (all 5) governance.tests.test_governance_gaps.TestForumRevisionCard.* (all 1) consilium_core.tests.test_core_controls_wave3.TestHistoryAndEvidencePack.* (all 4) consilium_core.tests.test_versioning.TestVersioning.* (all 9) consilium_core.tests.test_entities.TestEntityStructure.test_governed_entities_keep_their_change_history | K10: ✅ | L10: VREV-00001: FRM-2026-00010 Asset-Liability Committee reverted to DVER-00109 with a justification. 40 forum versions.
A11: G-10 | B11: CGF | C11: Mandatory | D11: The system shall support periodic review schedules including self-assessments, charter reviews and monitoring activities. It shall enforce an annual attestation, conducted in the first quarter, requiring Committee Chairs, Committee Secretaries and Forum Owners to review and confirm the accuracy of the forum inventory. | E11: Attestation engine with inventory and dual-review campaign types (reviews.open_inventory_attestation; attesting seats CHAIR, SECRETARY, FORUM_OWNER have can_attest). The office opens campaigns and generates tasks from /attestation-campaigns (reviews.open_forum_campaign, generate_forum_campaign_tasks). Tasks are answered and counter-signed in /tasks. Reminders follow each campaign's schedule (reminders.remind_attestation_campaigns, daily). The annual review is run from the forum (/forum-review#annual-review). The overdue chase goes to owners (reminders.remind_forum_reviews). last_attested_on is stamped. Missing: nothing enforces or schedules the first quarter. No job opens the Q1 campaign or flags a year with none. The screen defaults the due date to today + 45 days and accepts any dates. | F11: /attestation-campaigns /tasks /forum-review#annual-review | G11: /app/attestation-campaign — Consilium Administration workspace /app/forum-compliance-review — Governance workspace | H11: consilium/governance/reviews.py → open_inventory_attestation() consilium/governance/reviews.py → open_forum_campaign() consilium/governance/reviews.py → generate_forum_campaign_tasks() consilium/consilium_core/reminders.py → remind_attestation_campaigns() consilium/consilium_core/reminders.py → remind_forum_reviews() consilium/www/attestation_campaigns.py (portal page) consilium/www/tasks.py (portal page) consilium/consilium_core/attestation.py (module under the cited tests) consilium/consilium_core/inbox.py (module under the cited tests) consilium/governance/lifecycle.py (module under the cited tests) consilium/governance/inventory.py (module under the cited tests) consilium/consilium_core/doctype/attestation_campaign/attestation_campaign.py (Attestation Campaign) consilium/governance/doctype/forum_compliance_review/forum_compliance_review.py (Forum Compliance Review) | I11: (d) Not implemented, wholly or in a mandatory clause | J11: consilium_core.tests.test_attestation.TestAttestation.* (all 13) consilium_core.tests.test_attestation.TestUnconfiguredRecordsDoNotStopACampaign.* (all 3) consilium_core.tests.test_inbox.TestInboxAttestation.* (all 8) consilium_core.tests.test_inbox.TestSecondSignature.* (all 3) consilium_core.tests.test_inbox.TestCampaignAdministration.* (all 5) consilium_core.tests.test_w3_guides_core.TestCampaignReminderSchedule.* (all 4) consilium_core.tests.test_reminders.TestForumReviewReminders.* (all 1) governance.tests.test_lifecycle.TestAnnualReview.* (all 4) governance.tests.test_w3_guides.TestAnnualReviewFromTheForum.* (all 4) governance.tests.test_inventory.TestAttestationStamp.* (all 3) | K11: ✅ (not the Q1 clause) | L11: ACAM-00002 "Forum inventory attestation 2026": 22 attested, 3 with exceptions, 3 declined, 11 pending. It opened 2026-08-04, due 2026-10-03, so outside Q1. ACAM-00003 dual review; ACAM-00001 (2025) closed. Annual reviews FCR-2026-00015/16/17.
A12: G-11 | B12: CGF | C12: Mandatory | D12: The system shall provide a configurable disbandment workflow covering trigger scenarios (annual inventory review, self-assessment outcome, charter review, completion of mandate), validation of closure approvals from the delegating authority, sponsor, chair and — where applicable — the jurisdictional Chief Risk Officer, and capture of a formal disbandment plan as an uploaded, tracked artefact. | E12: /forum-disband (linked from /forum): lifecycle.raise_disbandment_plan (the governance office; five trigger scenarios; delegating authority, sponsor and chair required, jurisdictional CRO optional); attach_disbandment_file (only a file attached to this plan); record_disbandment_decision (approver or delegate); execute_forum_disbandment (waits for every approval; the forum becomes inactive, never deleted). | F12: /forum-disband?name=… /forum?name=… | G12: /app/disbandment-plan — Governance workspace /app/governance-forum — Governance workspace | H12: consilium/governance/lifecycle.py → raise_disbandment_plan() consilium/governance/lifecycle.py → attach_disbandment_file() consilium/governance/lifecycle.py → record_disbandment_decision() consilium/governance/lifecycle.py → execute_forum_disbandment() consilium/www/forum_disband.py (portal page) consilium/www/forum.py (portal page) consilium/governance/doctype/disbandment_plan/disbandment_plan.py (Disbandment Plan) consilium/governance/doctype/governance_forum/governance_forum.py (Governance Forum) | I12: (a) Through a purpose-built portal screen | J12: governance.tests.test_governance_gaps.TestDisbandmentPortal.* (all 8) governance.tests.test_lifecycle.TestDisbandment.* (all 5) governance.tests.test_entities.TestGovernanceEntities.test_a_disbandment_plan_needs_the_approvals_it_requires governance.tests.test_formation_portal.TestComplianceReviewThroughThePortal.test_a_disbanded_forum_is_not_reviewed_again | K12: ✅ | L12: FDIS-2026-00001: FRM-2026-00012 Outsourcing Oversight Forum disbanded 2026-04-21, successor FRM-2026-00013. FDIS-2026-00002 (FRM-2026-00013) live: delegating authority approved, sponsor and chair pending. Neither demo plan has a plan file attached.
... A72: O-7 | B72: Supplementary | C72: Supplementary | D72: Real-time regulatory updates, predictive analytics for emerging risks and automated governance risk assessment. | E72: /regulatory-updates: recent changes, citing documents and forums, rule-based candidate documents and sections; record_change saves through the Regulatory Requirement controller, whose fan-out tells owners of citing documents and forums (P-6); file import through /imports with profile IMPP-00001 and policy.regulatory_import.prepare_changes, same fan-out; optional AI suggestions recorded and applied only on a person's accept (decide, AI Suggestion Acceptance with version). /emerging-risks: trends (slope, z-score) and leading indicators over escalations, violations, monitoring and SLA breaches. Governance risk scores with configurable weights on /governance-gaps (ai.scoring.assess). Same guard and client as O-6. | F72: /regulatory-updates /imports /emerging-risks /governance-gaps | G72: /app/regulatory-requirement — Consilium Administration workspace /app/ai-suggestion-acceptance desk button — consilium/governance/doctype/forum_meeting/forum_meeting.js | H72: consilium/consilium_core/ai/regulatory.py → record_change() consilium/consilium_core/ai/regulatory.py → decide() consilium/www/regulatory_updates.py (portal page) consilium/www/imports.py (portal page) consilium/www/emerging_risks.py (portal page) consilium/www/governance_gaps.py (portal page) consilium/consilium_core/doctype/regulatory_requirement/regulatory_requirement.py (Regulatory Requirement) consilium/consilium_core/doctype/ai_suggestion_acceptance/ai_suggestion_acceptance.py (AI Suggestion Acceptance) | I72: (a) Through a purpose-built portal screen | J72: consilium_core.tests.test_ai_features.TestRegulatory.* (all 8) consilium_core.tests.test_ai_features.TestTrends.* (all 4) consilium_core.tests.test_ai_features.TestScoring.* (all 3) consilium_core.tests.test_ai_features.TestPages.* (all 1) consilium_core.tests.test_regulatory_change.TestRegulatoryChangeFanOut.* (all 6) consilium_core.tests.test_integrations.TestHorizonScanning.* (all 3) | K72: ✅ (AI suggestions tested against a stub endpoint only) | L72: REQ_OP_RESILIENCE changed 2026-09-18, cited by GDOC-00007, owner notified; 12 requirements; /emerging-risks 7 rising series, 7 indicators; scores for 13 forums and 14 policies. The AI endpoint is connected (see O-6), but no regulatory suggestion has been requested through it on the demo site. The horizon-scanning platform is reached through /horizon-scanning.

Sheet Summary
A1: Consilium — requirements coverage
A3: Generated on | B3: 2026-09-18 13:07
A4: Measured on (per source) | B4: 2026-09-18
A5: Source | B5: docs/delivery/REQUIREMENTS-COVERAGE.md (matrix); docs/product/01-requirements-baseline.md (statements); docs/delivery/EPICS.md (stories)
A6: Git commit | B6: 9abaca6 (2026-09-18) — working tree has uncommitted changes
A7: Coverage source state | B7: modified since last commit; sha256 14f9838e73e092bc…
A8: Test run (per source) | B8: Ran 1453 tests, OK — 1453 passed, 0 failed
A9: Generator | B9: scripts/coverage_to_xlsx.py — regenerate after editing the Markdown; do not hand-edit
A11: Reachability class by module (live formulas over 'All requirements') | H11: As stated in the source's §2 summary
A12: Module | B12: (a) Portal | C12: (b) Desk/config | D12: (c) Partly | E12: (d) Not impl. | F12: Total | H12: a | I12: b | J12: c | K12: d | L12: Total | M12: Agrees? | O12: Chart data | P12: (a) | Q12: (b) | R12: (c) | S12: (d)
A13: CGF — Governance | B13: =COUNTIFS('All requirements'!$B$2:$B$500,"CGF",'All requirements'!$H$2:$H$500,"a") | C13: =COUNTIFS('All requirements'!$B$2:$B$500,"CGF",'All requirements'!$H$2:$H$500,"b") | D13: =COUNTIFS('All requirements'!$B$2:$B$500,"CGF",'All requirements'!$H$2:$H$500,"c") | E13: =COUNTIFS('All requirements'!$B$2:$B$500,"CGF",'All requirements'!$H$2:$H$500,"d") | F13: =COUNTIFS('All requirements'!$B$2:$B$500,"CGF") | H13: 11 | I13: 1 | J13: 4 | K13: 3 | L13: 19 | M13: =IF(COUNT(H13:L13)=0,"not stated",IF(AND(B13=H13,C13=I13,D13=J13,E13=K13,F13=L13),"Yes","NO")) | O13: CGF | P13: =B13 | Q13: =C13 | R13: =D13 | S13: =E13
A14: POL — Policy | B14: =COUNTIFS('All requirements'!$B$2:$B$500,"POL",'All requirements'!$H$2:$H$500,"a") | C14: =COUNTIFS('All requirements'!$B$2:$B$500,"POL",'All requirements'!$H$2:$H$500,"b") | D14: =COUNTIFS('All requirements'!$B$2:$B$500,"POL",'All requirements'!$H$2:$H$500,"c") | E14: =COUNTIFS('All requirements'!$B$2:$B$500,"POL",'All requirements'!$H$2:$H$500,"d") | F14: =COUNTIFS('All requirements'!$B$2:$B$500,"POL") | H14: 19 | I14: 3 | J14: 3 | K14: 1 | L14: 26 | M14: =IF(COUNT(H14:L14)=0,"not stated",IF(AND(B14=H14,C14=I14,D14=J14,E14=K14,F14=L14),"Yes","NO")) | O14: POL | P14: =B14 | Q14: =C14 | R14: =D14 | S14: =E14
A15: ESC — Escalation | B15: =COUNTIFS('All requirements'!$B$2:$B$500,"ESC",'All requirements'!$H$2:$H$500,"a") | C15: =COUNTIFS('All requirements'!$B$2:$B$500,"ESC",'All requirements'!$H$2:$H$500,"b") | D15: =COUNTIFS('All requirements'!$B$2:$B$500,"ESC",'All requirements'!$H$2:$H$500,"c") | E15: =COUNTIFS('All requirements'!$B$2:$B$500,"ESC",'All requirements'!$H$2:$H$500,"d") | F15: =COUNTIFS('All requirements'!$B$2:$B$500,"ESC") | H15: 13 | I15: 2 | J15: 2 | K15: 2 | L15: 19 | M15: =IF(COUNT(H15:L15)=0,"not stated",IF(AND(B15=H15,C15=I15,D15=J15,E15=K15,F15=L15),"Yes","NO")) | O15: ESC | P15: =B15 | Q15: =C15 | R15: =D15 | S15: =E15
A16: Mandatory total | B16: =COUNTIFS('All requirements'!$C$2:$C$500,"Mandatory",'All requirements'!$H$2:$H$500,"a") | C16: =COUNTIFS('All requirements'!$C$2:$C$500,"Mandatory",'All requirements'!$H$2:$H$500,"b") | D16: =COUNTIFS('All requirements'!$C$2:$C$500,"Mandatory",'All requirements'!$H$2:$H$500,"c") | E16: =COUNTIFS('All requirements'!$C$2:$C$500,"Mandatory",'All requirements'!$H$2:$H$500,"d") | F16: =COUNTIFS('All requirements'!$C$2:$C$500,"Mandatory") | H16: 43 | I16: 6 | J16: 9 | K16: 6 | L16: 64 | M16: =IF(COUNT(H16:L16)=0,"not stated",IF(AND(B16=H16,C16=I16,D16=J16,E16=K16,F16=L16),"Yes","NO")) | O16: Supplementary | P16: =B17 | Q16: =C17 | R16: =D17 | S16: =E17
A17: Supplementary (O-…) | B17: =COUNTIFS('All requirements'!$B$2:$B$500,"Supplementary",'All requirements'!$H$2:$H$500,"a") | C17: =COUNTIFS('All requirements'!$B$2:$B$500,"Supplementary",'All requirements'!$H$2:$H$500,"b") | D17: =COUNTIFS('All requirements'!$B$2:$B$500,"Supplementary",'All requirements'!$H$2:$H$500,"c") | E17: =COUNTIFS('All requirements'!$B$2:$B$500,"Supplementary",'All requirements'!$H$2:$H$500,"d") | F17: =COUNTIFS('All requirements'!$B$2:$B$500,"Supplementary") | H17: 5 | I17: 0 | J17: 0 | K17: 2 | L17: 7 | M17: =IF(COUNT(H17:L17)=0,"not stated",IF(AND(B17=H17,C17=I17,D17=J17,E17=K17,F17=L17),"Yes","NO"))
A18: Left: computed from the rows. Right: typed in the source's summary table and copied here as-is, so a stale summary in the Markdown shows up as 'NO'.
A20: Test evidence
A21: Evidence | B21: Mandatory | C21: Supplementary | D21: All
A22: At least one direct test, all passing | B22: =COUNTIFS('All requirements'!$C$2:$C$500,"Mandatory",'All requirements'!$N$2:$N$500,"Direct test") | C22: =COUNTIFS('All requirements'!$B$2:$B$500,"Supplementary",'All requirements'!$N$2:$N$500,"Direct test") | D22: =COUNTIFS('All requirements'!$N$2:$N$500,"Direct test")
A23: No direct test | B23: =COUNTIFS('All requirements'!$C$2:$C$500,"Mandatory",'All requirements'!$N$2:$N$500,"No direct test") | C23: =COUNTIFS('All requirements'!$B$2:$B$500,"Supplementary",'All requirements'!$N$2:$N$500,"No direct test") | D23: =COUNTIFS('All requirements'!$N$2:$N$500,"No direct test")
A24: Failing tests | B24: =COUNTIFS('All requirements'!$C$2:$C$500,"Mandatory",'All requirements'!$N$2:$N$500,"Failing test") | C24: =COUNTIFS('All requirements'!$B$2:$B$500,"Supplementary",'All requirements'!$N$2:$N$500,"Failing test") | D24: =COUNTIFS('All requirements'!$N$2:$N$500,"Failing test")
A25: …of which the pass is qualified (e.g. 'engine only') | B25: =COUNTIFS('All requirements'!$C$2:$C$500,"Mandatory",'All requirements'!$L$2:$L$500,"Pass (qualified)") | C25: =COUNTIFS('All requirements'!$B$2:$B$500,"Supplementary",'All requirements'!$L$2:$L$500,"Pass (qualified)") | D25: =COUNTIFS('All requirements'!$L$2:$L$500,"Pass (qualified)")
A26: Suite as measured: 1453 test methods run, outcome OK (typed from the source's Method section). A passing test proves only the part of a requirement it exercises.
A28: Backlog stories by status (live formulas over 'Epics')
A29: Status | B29: Stories
A30: Done | B30: =COUNTIFS('Epics'!$F$2:$F$1000,"Done*")
A31: Partial | B31: =COUNTIFS('Epics'!$F$2:$F$1000,"Partial*")
A32: In progress | B32: =COUNTIFS('Epics'!$F$2:$F$1000,"In progress*")
A33: Not started | B33: =COUNTIFS('Epics'!$F$2:$F$1000,"Not started*")
A34: Blocked | B34: =COUNTIFS('Epics'!$F$2:$F$1000,"Blocked*")
A35: No status recorded | B35: =COUNTIFS('Epics'!$A$2:$A$1000,"E*",'Epics'!$F$2:$F$1000,"")
A36: Total | B36: =COUNTIFS('Epics'!$A$2:$A$1000,"E*")
A38: Legend
A39: Class a | B39: Reachable through a purpose-built portal screen: the CS screens the trace names exist and do their part. Desk is used only where the trace names a DK surface.
A40: Class b | B40: Reachable through the desk, configuration or a scheduled job by design: the trace names only DK or BG surfaces for the key action.
A41: Class c | B41: Partly reachable. The backend exists, but a step has no screen, is desk-only where the trace calls for a custom screen, or is reachable only from code.
A42: Class d | B42: Not implemented, wholly or in a mandatory clause. The class is the weakest mandatory clause; the "What satisfies it" cell names the missing clause.
A43: Pass | B43: ✅ — the cited tests exist and passed in the measured run.
A44: Pass (qualified) | B44: ✅ with a qualifier such as '(engine only)' or '(flags only)': the tests pass but do not reach the missing clause.
A45: No direct test | B45: ⚠️ — nothing tests this requirement directly.
A46: Fail | B46: ❌ — a cited test failed.
A47: Priority | B47: All 64 G/P/E requirements are Mandatory; O-1…O-7 are supplementary requirements brought into scope (baseline Appendix A).
A48: Cited test methods (est.) | B48: Sum of '(all N)' plus individually named methods in the Test(s) cell. An estimate: shared engine tests are counted under every requirement that cites them.
A50: Sources
A51: File | D51: State | F51: Last commit | I51: SHA-256 (first 16)
A52: docs/delivery/REQUIREMENTS-COVERAGE.md | D52: modified since last commit | F52: 50d757c 2026-09-18 | I52: 14f9838e73e092bc
A53: docs/product/01-requirements-baseline.md | D53: clean | F53: 32c76ac 2026-09-17 | I53: a0ceb6b98eea9665
A54: docs/delivery/EPICS.md | D54: modified since last commit | F54: 50d757c 2026-09-18 | I54: 3075b8c91a430af0
A55: Parse warnings: none.

Sheet All requirements
A1: ID | B1: Module | C1: Priority | D1: Short title | E1: Baseline title | F1: Requirement (baseline statement) | G1: What satisfies it | H1: Class | I1: Class meaning | J1: Demo data / workflow | K1: Test(s) | L1: Result | M1: Result as measured | N1: Test evidence | O1: Cited test methods (est.) | P1: Planned satisfaction (baseline) | Q1: Δ decision | R1: Gap sections citing it | S1: Epics tracing it | T1: Stories tracing it
A2: G-1 | B2: CGF | C2: Mandatory | D2: Central forum repository, role-based access | E2: Forum Repository | F2: The system shall provide a centralized, searchable repository of every committee and governance forum, holding forum details, charter documents and associated metadata. Access, visibility and permitted actions shall be governed by role-based access control. | G2: Governance Forum with DocPerm rows; /forums register and /forum detail over the permission-checked REST API; www/forum.py throws for a viewer without read access and offers Edit only with write permission. | H2: a | I2: (a) Portal screen | J2: 14 forums, from FRM-2026-00001 Board of Directors down to working groups (FRM-2026-00013). | K2: governance.tests.test_entities.TestGovernanceEntities (all 19); governance.tests.test_inventory.TestSearchAndFilter.test_search_respects_permissions; consilium_core.tests.test_portal_pages.TestReaderWithoutAccess (all 2) | L2: Pass | M2: ✅ | N2: Direct test | O2: 25 | P2: Config — Governance Forum DocType, attachment handling and the permission engine are native; the register screen is a custom Bootstrap table. | S2: E6 | T2: 6
A3: G-2 | B3: CGF | C3: Mandatory | D3: Advanced search and filter | E3: Search and Retrieval | F3: The system shall provide advanced search and filtering of forums by any indexed metadata field. | G3: /forums filters by type, status, cadence, risk category, operating group and standing, plus the four multi-valued dimensions (inventory.inventory_filters, inventory.tagged_forum_names, intersecting). Free-text search over name, code and mandate, also taken from ?q=. The header's global search finds a forum by identifier or name from any page (consilium_core/search.py). Retired taxonomy values are marked, not offered as new. Paged server-side, with Export CSV. | H3: a | I3: (a) Portal screen | J3: /forums?standing=overdue lists FRM-2026-00008 Model Risk Committee (review due 2026-08-14). | K3: governance.tests.test_inventory.TestSearchAndFilter (all 4); governance.tests.test_governance_gaps.TestInventoryReads.test_tagged_filters_intersect, …test_tagged_names_respect_permission, …test_filter_values_include_retired_ones_marked; consilium_core.tests.test_global_search.TestGlobalSearch (all 9) | L3: Pass | M3: ✅ | N3: Direct test | O3: 19 | P3: Config + Build — native list filtering and report views on Desk; a hand-built filter/search/sort/paginate control on the custom Forum Register. | Q3: Δ | S3: E6, E35 | T3: 11
A4: G-3 | B4: CGF | C4: Mandatory | D4: Forum tagging with controlled taxonomies | E4: Forum Tagging | F4: The system shall allow a forum to be tagged with controlled metadata drawn from standard taxonomies, with dependent-field behaviour and dropdown-controlled selection. Minimum attributes: forum identifier, name, type, description, meeting cadence, chair, primary risk category, legal entity, owning organisation (operating group) and owning organisation (line of business). | G4: Link fields plus four multi-select child tables (business unit, risk type, legal entity, jurisdiction). Operating-group and line-of-business validation. Captured in /create-forum and on desk; shown on /forum. Retired values are not offered (taxonomy standard_queries hook). | H4: a | I4: (a) Portal screen | J4: FRM-2026-00007 Technology and Cyber Risk Committee: type MGMT_CTTE, regulatory-required, 2 business units and 3 risk types. | K4: test_entities.TestGovernanceEntities.test_four_dimensions_are_multi_valued_and_two_are_not, …test_the_owning_organisation_must_be_an_operating_group, …test_a_line_of_business_must_sit_under_its_operating_group; consilium_core.tests.test_entities.TestTaxonomies (all 9); consilium_core.tests.test_taxonomy.TestActiveOnlySearch (all 6) | L4: Pass | M4: ✅ | N4: Direct test | O4: 20 | P4: Config — Link fields to Core taxonomy DocTypes plus child multi-select tables. | Q4: Δ | S4: E3, E6 | T4: 11
A5: G-4 | B5: CGF | C5: Mandatory | D5: Forum mapping; regulatory-required with dependent capture | E5: Forum Mapping | F5: The system shall allow a forum to be mapped to related forums (upstream and downstream), to be flagged as regulatory-required with dependent capture of the applicable regulatory requirements. | G5: parent_forum, Forum Link (upstream and downstream), and Forum Regulatory Requirement, required when the flag is set. inventory.interconnectivity is drawn as SVG on /forum (Linkages tab). Links are edited on desk. | H5: a | I5: (a) Portal screen | J5: 15 Forum Link rows. FRM-2026-00005 Executive Risk Committee answers to FRM-2026-00004 and FRM-2026-00002 and has five sub-committees. 7 regulatory-required forums, for example FRM-2026-00010 with 2 requirements. | K5: test_entities.…test_regulatory_detail_becomes_required_when_the_flag_is_set, …test_a_forum_cannot_be_its_own_ancestor, …test_a_link_takes_its_direction_from_the_field_it_sits_in, …test_a_forum_cannot_link_to_itself; test_inventory.TestRelationships (all 2) | L5: Pass | M5: ✅ | N5: Direct test | O5: 6 | P5: Config — self-referencing child table Forum Link; Forum Regulatory Requirement child table gated on a check field. | S5: E6 | T5: 6
A6: G-5 | B6: CGF | C6: Mandatory | D6: Committee formation: intake, 5-criteria evaluation, evidence, exceptions, status | E6: Committee Formation | F6: The system shall support the committee formation process: structured intake, evaluation against defined criteria, capture of approval evidence, exception handling and status tracking. Evaluation criteria: gap in risk or governance coverage; duplication with existing forums; clear escalation and reporting pathways; alignment with the risk management framework, risk taxonomy and policy structure; resource feasibility. Charter drafts must be reviewable by the Risk Governance Office for completeness and appropriateness before approval. Acceptable approval evidence includes email, meeting minutes and signed documents. Disputes and exceptions resolve through the Head of Risk Governance. | G6: Committee Formation Request + Formation Evaluation (5 criteria seeded) + formation.py. /create-forum → /formation-requests → /formation-request covers findings, return and respond, approval steps, exception to the designated authority, charter challenge, approve, reject and withdraw. Approval creates a draft forum. Gap: Charter Approval Evidence rows are captured on desk only (DK-1 is in the trace). | H6: a | I6: (a) Portal screen | J6: One request at each stage: CFR-2026-00006 Draft; 00004 Under Evaluation; 00003 Returned To Originator; 00002 Pending Approval; 00005 Rejected; 00001 Approved → FRM-2026-00014 Data Governance Council, with bypass EXCA-00001. | K6: governance.tests.test_formation (all 27: TestIntake, TestEvaluation, TestReturnToOriginator, TestApprovalRoute, TestExceptionRoute, TestApprovalCreatesTheForum); governance.tests.test_formation_portal (all 35) | L6: Pass | M6: ✅ | N6: Direct test | O6: 64 | P6: Config + Build — Committee Formation Request with a configured multi-state workflow; Forum Evaluation child table; Committee Charter with attached approval evidence. Build: the gating logic that prevents progression. | Q6: Δ | S6: E7 | T6: 6
A7: G-6 | B7: CGF | C7: Mandatory | D7: Admin-configurable workflows, no code | E7: Configurable Automated Workflow | F7: The system shall support administratively configurable automated workflows for establishing, maintaining and disbanding forums, including approvals and escalations, without custom development. | G7: Formation Approval Route (steps, sequence and mode as data); Workflow State Flag (130 rows); Watched Field Set; disbandment trigger scenarios and approver roles are select options. Nothing branches on a state label. All on desk. | H7: b | I7: (b) Desk / config / job by design | J7: "Standard Formation Approval" route (request type Any). CFR-2026-00002 shows the three steps it raised. | K7: test_formation.TestApprovalRoute.test_the_steps_are_configuration, …test_a_route_change_changes_the_steps_without_a_deployment; consilium_core.tests.test_state_flags.TestStateFlags (all 7); governance.tests.test_lifecycle.TestStateFlags (all 3); test_lifecycle.TestWatchedFields (all 5) | L7: Pass | M7: ✅ | N7: Direct test | O7: 19 | P7: Native + Config — the framework's Workflow engine (states, transitions, role gates) is a configuration record, editable by an administrator. | Q7: Δ | S7: E7 | T7: 6
A8: G-7 | B8: CGF | C8: Mandatory | D8: Governance office controls: completeness, overlap check, charter challenge before approval, validate approvals | E8: Risk Governance Office Controls | F8: The system shall prevent progression of a formation request when required information, approvals or evidence are incomplete or inconsistent. It shall validate intake completeness, check the request against the existing forum inventory for overlap or conflict, allow review and challenge of the draft charter before the requester seeks final approval, and validate submitted approvals against the intake record and charter before the forum inventory is updated. | G8: formation.approval_blockers covers: unassessed criteria; completeness confirmation; undecided steps; refused steps not bypassed; and an uncleared charter challenge (charters.uncleared_challenges). The challenge is recorded on /formation-request (charters.record_charter_challenge). An open challenge also blocks a favourable compliance decision (lifecycle.refuse_standing_over_open_challenge). Gap: the charter's approval evidence (in charters.clearance_blockers) is shown on /forum but is not a formation approval blocker. | H8: a | I8: (a) Portal screen | J8: CFR-2026-00002 is held by CHT-2026-00014 "Changes Requested" and by an open Delegating Authority step. CHT-2026-00007 (FRM-2026-00007) "Changes Requested". | K8: test_formation.TestIntake.test_submission_runs_the_overlap_check; TestEvaluation (all 4); governance.tests.test_governance_gaps.TestFormationCharterGate (all 2), TestStandingGate (all 3); governance.tests.test_wave3_governance.TestCharterChallengeOnTheRequest (all 2); governance.tests.test_charters.TestEffectiveChallenge (all 4) | L8: Pass | M8: ✅ | N8: Direct test | O8: 19 | P8: Build — server-side validation on workflow transition; duplicate-detection query against the forum register; completeness gate on the evaluation child table. | S8: E7, E33 | T8: 7
A9: G-8 | B9: CGF | C9: Mandatory | D9: Multi-step, sequential or parallel approval; path by materiality and forum type | E9: Configurable Review and Approval Workflow | F9: The system shall support a multi-step approval process across stakeholders and roles, with sequential or parallel approvals, capturing charter approval. Approval paths may differ by materiality of change and by forum type. | G9: Route steps become Core Approval Decisions. Sequential order is enforced in approvals.record_decision (waiting_on, is_turn). Parallel steps and peers sharing a sequence number do not wait. Role-based steps form a queue. Steps are decided on /formation-request by the assignee, a queue member or a delegate. A bypass needs an Exception Authorisation, waives only its own step, and cannot be made by the step's own holder. Missing: the path cannot differ by forum type or by materiality of change. formation.resolve_route selects only by request_type (Any, Create, Modify, Retire), and Formation Approval Route has no forum-type or materiality field. | H9: d | I9: (d) Not implemented (whole or mandatory part) | J9: CFR-2026-00002: Risk Governance Office Evaluation (seq 1) approved, Sponsor Endorsement (seq 2) approved, Delegating Authority (seq 2) pending. CFR-2026-00001: Sponsor step bypassed under EXCA-00001. | K9: test_formation.TestApprovalRoute (all 5); test_formation_portal.TestApprovalThroughThePortal (all 5); consilium_core.tests.test_core_controls_wave3.TestSequentialApprovals (all 6); governance.tests.test_wave3_governance.TestFormationStepOrder (all 4); governance.tests.test_w3_guides.TestABypassWaivesOnlyItsOwnStep (all 1), TestNobodyBypassesTheirOwnStep (all 2), TestARoleIsAQueue (all 5); consilium_core.tests.test_services.TestApprovals (all 5) | L9: Pass (qualified) | M9: ✅ (not the path-selection clause) | N9: Direct test | O9: 37 | P9: Config + Build — workflow states and role-gated transitions; build for conditional path selection by change materiality. | R9: Class (d), No direct test | S9: E7 | T9: 6
A10: G-9 | B10: CGF | C10: Mandatory | D10: Full history, attributed; archivable prior versions; revert a forum record | E10: Version Control, Audit History and Accountability | F10: The system shall track every change to a forum, maintain complete history, and log every user action with a timestamp and attributed actor. Prior versions shall be archivable and viewable. The system shall additionally allow an authorised user to revert a forum record to a previous version. | G10: A revision.snapshot doc event on Governance Forum writes a version chain. /forum History tab offers a revision history with Revert (revision.history and revision.revert: reason required, governance office only; lifecycle and derived fields are never restored; reverting a watched field sends the forum back for review). Record history (evidence.record_history, now including notifications) and an evidence-pack ZIP with a SHA-256 manifest (evidence.export_pack). | H10: a | I10: (a) Portal screen | J10: VREV-00001: FRM-2026-00010 Asset-Liability Committee reverted to DVER-00109 with a justification. 40 forum versions. | K10: consilium_core.tests.test_revision.TestForumRevision (all 5); governance.tests.test_governance_gaps.TestForumRevisionCard (all 1); consilium_core.tests.test_core_controls_wave3.TestHistoryAndEvidencePack (all 4); consilium_core.tests.test_versioning.TestVersioning (all 9); consilium_core.tests.test_entities.TestEntityStructure.test_governed_entities_keep_their_change_history | L10: Pass | M10: ✅ | N10: Direct test | O10: 25 | P10: Native + Build — field-level version log and comment threads are native; revert is a build. | Q10: Δ | S10: E4, E30 | T10: 6
A11: G-10 | B11: CGF | C11: Mandatory | D11: Periodic reviews; annual Q1 inventory attestation by chairs, secretaries, owners | E11: Forum Maintenance | F11: The system shall support periodic review schedules including self-assessments, charter reviews and monitoring activities. It shall enforce an annual attestation, conducted in the first quarter, requiring Committee Chairs, Committee Secretaries and Forum Owners to review and confirm the accuracy of the forum inventory. | G11: Attestation engine with inventory and dual-review campaign types (reviews.open_inventory_attestation; attesting seats CHAIR, SECRETARY, FORUM_OWNER have can_attest). The office opens campaigns and generates tasks from /attestation-campaigns (reviews.open_forum_campaign, generate_forum_campaign_tasks). Tasks are answered and counter-signed in /tasks. Reminders follow each campaign's schedule (reminders.remind_attestation_campaigns, daily). The annual review is run from the forum (/forum-review#annual-review). The overdue chase goes to owners (reminders.remind_forum_reviews). last_attested_on is stamped. Missing: nothing enforces or schedules the first quarter. No job opens the Q1 campaign or flags a year with none. The screen defaults the due date to today + 45 days and accepts any dates. | H11: d | I11: (d) Not implemented (whole or mandatory part) | J11: ACAM-00002 "Forum inventory attestation 2026": 22 attested, 3 with exceptions, 3 declined, 11 pending. It opened 2026-08-04, due 2026-10-03, so outside Q1. ACAM-00003 dual review; ACAM-00001 (2025) closed. Annual reviews FCR-2026-00015/16/17. | K11: consilium_core.tests.test_attestation.TestAttestation (all 13), TestUnconfiguredRecordsDoNotStopACampaign (all 3); consilium_core.tests.test_inbox.TestInboxAttestation (all 8), TestSecondSignature (all 3), TestCampaignAdministration (all 5); consilium_core.tests.test_w3_guides_core.TestCampaignReminderSchedule (all 4); consilium_core.tests.test_reminders.TestForumReviewReminders (all 1); governance.tests.test_lifecycle.TestAnnualReview (all 4); governance.tests.test_w3_guides.TestAnnualReviewFromTheForum (all 4); test_inventory.TestAttestationStamp (all 3) | L11: Pass (qualified) | M11: ✅ (not the Q1 clause) | N11: Direct test | O11: 54 | P11: Build — the shared attestation campaign/task engine, with a CGF inventory campaign type; scheduled job generates tasks and reminders. | Q11: Δ | R11: Class (d), No direct test | S11: E8, E18, E28 | T11: 13
A12: G-11 | B12: CGF | C12: Mandatory | D12: Configurable disbandment: triggers, approvals, plan artefact | E12: Committee Disbanding | F12: The system shall provide a configurable disbandment workflow covering trigger scenarios (annual inventory review, self-assessment outcome, charter review, completion of mandate), validation of closure approvals from the delegating authority, sponsor, chair and — where applicable — the jurisdictional Chief Risk Officer, and capture of a formal disbandment plan as an uploaded, tracked artefact. | G12: /forum-disband (linked from /forum): lifecycle.raise_disbandment_plan (the governance office; five trigger scenarios; delegating authority, sponsor and chair required, jurisdictional CRO optional); attach_disbandment_file (only a file attached to this plan); record_disbandment_decision (approver or delegate); execute_forum_disbandment (waits for every approval; the forum becomes inactive, never deleted). | H12: a | I12: (a) Portal screen | J12: FDIS-2026-00001: FRM-2026-00012 Outsourcing Oversight Forum disbanded 2026-04-21, successor FRM-2026-00013. FDIS-2026-00002 (FRM-2026-00013) live: delegating authority approved, sponsor and chair pending. Neither demo plan has a plan file attached. | K12: governance.tests.test_governance_gaps.TestDisbandmentPortal (all 8); governance.tests.test_lifecycle.TestDisbandment (all 5); test_entities.…test_a_disbandment_plan_needs_the_approvals_it_requires; test_formation_portal.TestComplianceReviewThroughThePortal.test_a_disbanded_forum_is_not_reviewed_again | L12: Pass | M12: ✅ | N12: Direct test | O12: 17 | P12: Config + Build — terminal workflow state with its own approval path; Disbandment Plan DocType; build for the approval-completeness gate and the retention consequence. | S12: E8 | T12: 5
A13: G-12 | B13: CGF | C13: Mandatory | D13: Reporting and dashboards: status, coverage, compliance, performance; drill-down; export | E13: Reporting and Dashboards | F13: The system shall provide reporting and dashboards for oversight of forums enterprise-wide: status, coverage, compliance and performance metrics; filtering, aggregation and drill-down by forum type, status, legal entity, risk coverage, ownership and review or attestation status; current and historical views including forums in formation, active forums, upcoming reviews, overdue actions and service-level performance; export of reports and artefacts for management, audit and regulatory needs. | G13: /reports: forums awaiting review, overdue, regulatory-required, disbanded; by compliance status and by type; coverage matrix of risk category by owning group, with empty cells highlighted. Every figure links to the filtered /forums. Also /governance-gaps (ai.gaps.detect: coverage, forum, policy and regulatory gaps; ai.scoring.assess); /formation-requests for forums in formation; /attestation-campaigns board for attestation status. Export CSV on /forums exports the matching rows through the permission-checked list (up to 5,000 rows, formula-safe). Gap: no service-level performance for forums or formation (no SLA Definition targets either doctype). | H13: c | I13: (c) Partly reachable | J13: FRM-2026-00007 Non-Compliant; FRM-2026-00013 Pending; FRM-2026-00011 and FRM-2026-00014 Draft; FRM-2026-00012 Disbanded; FRM-2026-00008 overdue. | K13: consilium_core.tests.test_ai_features.TestGaps.test_forum_policy_regulatory_and_coverage_gaps_are_found; consilium_core.tests.test_ai_features.TestPages (all 1); consilium_core.tests.test_portal_pages.TestAdministrator.test_every_page_renders_with_its_key_sections | L13: Pass (qualified) | M13: ✅ (gap rules and page render only; no forum figure is tested) | N13: Direct test | O13: 6 | P13: Native + Build — native report builder, query reports, dashboard charts and export on Desk; custom Bootstrap dashboard screens for the daily-use views. | R13: Class (c), No direct test | S13: E10, E20 | T13: 9
A14: G-13 | B14: CGF | C14: Mandatory | D14: RBAC with delegates; groupings; nomination of delegates | E14: Role-Based Access Control | F14: The system shall provide role-based access for individuals and their delegates (Committee Secretary, Forum Owner, Reviewer, Approver, Viewer, Administrator). It shall support grouping users by role and attribute (line of business, first/second line of defence, legal, compliance, voting versus non-voting). Chairs, sponsors and secretaries shall be able to nominate delegates for administrative tasks. | G14: Roles (Committee Secretary, Forum Owner, Compliance Reviewer, Governance Viewer, Risk Governance Office, Consilium Administrator, Consilium Audit and others). Seat roles carry vote, quorum and attest flags. Authority Delegation with a validity window (delegation.resolve_actor). Seat delegates on Forum Membership. Gap: chairs and sponsors cannot nominate a delegate themselves. Only System Manager and Consilium Administrator may create Authority Delegation. Seat delegates are set on desk by the Committee Secretary or the governance office. | H14: c | I14: (c) Partly reachable | J14: 23 personas. ADEL-00001…00004 (ADEL-00002 expired). FMEM-00031 on FRM-2026-00005 has a standing delegate. | K14: consilium_core.tests.test_delegation.TestDelegation (all 13); consilium_core.tests.test_entities.TestPermissions (all 5); governance.tests.test_membership.TestDelegation (all 3); governance.tests.test_voting.TestDelegatedVoting (all 3); test_w3_guides.TestARoleIsAQueue (all 5) | L14: Pass | M14: ✅ | N14: Direct test | O14: 33 | P14: Native + Config + Build — native role/permission engine and user groups; forum-scoped accountability roles are modelled as membership rows; build for delegation validity windows. | Q14: Δ | R14: Class (c) | S14: E2, E9 | T14: 11
A15: G-14 | B15: CGF | C15: Mandatory | D15: Configurable, templated, automated notifications (approvals, reviews, escalations, meetings, attestation, charter reviews) | E15: Notifications | F15: The system shall send configurable, templated, automated notifications for approvals, reviews, escalations, meeting schedules, annual attestation and charter reviews. | G15: Notification Template per event (49, admin-editable per channel; notification.notify). There is an e-mail adapter over SMTP or Microsoft Graph, falling back to the record channel, with retry. Every caller now raises an event; none sends hard-coded text. Governance events: formation returned, approval requested, exception raised, approved and rejected; forum review recorded, returned for review and disbanded; disbandment approval requested (governance.disbandment.approval_requested, from lifecycle.raise_disbandment); forum review overdue; attestation open and second signature missing; attestation task reminder. Missing: no notification for meeting schedules or charter reviews (no event code, template or caller). | H15: d | I15: (d) Not implemented (whole or mandatory part) | J15: 201 dispatches: 178 EMAIL, 23 RECORD. For example "Formation approval requested" (8), "Compliance review recorded" (34). The 2 "Forum disbandment awaits your approval" dispatches were written by the demo load before that notice was templated. Reminder Log row for governance.forum_review.overdue on FRM-2026-00008. | K15: governance.tests.test_wave3_governance.TestTemplatedNotices (all 3); consilium_core.tests.test_notification_templates.TestSeeding (all 2), TestEventApi (all 10), TestTemplateFailures (all 5), TestEmailRetry (all 3); consilium_core.tests.test_notification.TestNotification (all 6); test_formation.TestReturnToOriginator.test_the_originator_is_notified; test_lifecycle.TestWatchedFields.test_compliance_is_notified_and_a_task_is_raised; governance.tests.test_governance_gaps.TestDisbandmentPortal.test_raising_names_g11s_approvers_and_asks_them | L15: Pass (qualified) | M15: ✅ (what exists; nothing tests the missing meeting and charter notices) | N15: Direct test | O15: 36 | P15: Native + Config + Build — native notification definitions and email queue; build for the pluggable channel abstraction. | Q15: Δ | R15: Class (d), No direct test | S15: E9, E19, E29, E36 | T15: 18
A16: G-15 | B16: CGF | C16: Mandatory | D16: Attach any documents, with version control and audit log; retain all | E16: Document Management | F16: The system shall allow documents to be attached without restriction on type or count — templates, charters and mandates, agendas, meeting minutes and related material — with version control, and shall show an audit log of all activity. All documents and history shall be retained. | G16: Native attachments and activity log. On /forum Documents: start a charter (charters.start_forum_charter) and take a new charter version with a change summary (charters.publish_charter_version, only a file attached to that charter; this reopens the challenge). Minutes are versioned through the desk button "Record minutes" (meetings.record_meeting_minutes). Meeting agenda file. Deletion guarded. | H16: a | I16: (a) Portal screen | J16: 14 charters, 17 charter versions (CHT-2026-00005, CHT-2026-00007 and CHT-2026-00011 have 2 each). 67 meetings, 38 with a minutes version (for example FMTG-2026-00035). | K16: governance.tests.test_governance_gaps.TestCharterPortal (all 9); governance.tests.test_charters.TestCharterVersions (all 2); governance.tests.test_regressions.TestMinutes (all 3) | L16: Pass | M16: ✅ | N16: Direct test | O16: 17 | P16: Native + Build — native attachment handling and activity log; build for the document version chain and its retention linkage. | Q16: Δ | S16: E5, E33 | T16: 6
A17: G-16 | B17: CGF | C17: Mandatory | D17: Retention per policy; WORM for the retention period | E17: Data and Document Retention | F17: The system shall retain data and documents in accordance with the applicable retention policy and requirements, and shall hold documents and data in a write-once, read-many form for the duration of their retention period. | G17: Retention class, assignment and legal hold on desk. guard_modification and guard_deletion on every doctype. Hash-chained Archive Record. The daily retention.flag_due_for_disposal puts past-retention archives up for approved disposition (held when under legal hold) and deletes nothing. Gap: nothing in the application creates an Archive Record. execute_disposition and release_hold have no caller outside tests, so an approved disposal cannot be carried out from any screen. 0 Retention Assignments on the demo site, so no governance record is actually under retention or WORM (retention_lock reads assignments, not the forum's retention_class field). | H17: c | I17: (c) Partly reachable | J17: 5 retention classes (GOV-MINUTES requires WORM). All 14 forums carry retention_class GOV-FORUM. 0 assignments, 0 archives, 0 dispositions. | K17: consilium_core.tests.test_retention.TestRetention (all 14); consilium_core.tests.test_core_controls_wave3.TestScheduledDisposalReview (all 5) | L17: Pass | M17: ✅ | N17: Direct test | O17: 21 | P17: Build — retention classes, retention schedule evaluation, legal holds, immutable archive records and disposition, built in platform. | Q17: Δ | R17: Class (c) | S17: E5 | T17: 5
A18: G-17 | B18: CGF | C18: Mandatory | D18: Governance intake form with minimum fields; office checks completeness | E18: Governance Intake Form | F18: The system shall allow a request to create, modify or retire a forum to be submitted, with configurable content and a configurable workflow. Intake shall capture at minimum: whether the request is to create a new committee as defined by the enterprise governance standard; the rationale; the purpose and scope; the proposed responsibilities; the delegating authority; whether delegating-authority approval has been obtained (not required at submission); the proposed timeline; and the expected date of the first meeting. The Risk Governance Office shall check completeness and appropriateness before the request proceeds. | G18: /create-forum wizard (guidance, required fields, draft save, compliance-review warning) → formation.submit_request; answer to a return via respond_to_returned_request. Completeness is confirmed on /formation-request. Originators without a governance role can open, answer and withdraw their own request. | H18: a | I18: (a) Portal screen | J18: CFR-2026-00006 Payments Innovation Forum (draft); CFR-2026-00003 returned with questions. | K18: test_formation.TestIntake (all 5); test_formation_portal.TestReturnAndRespond (all 4), TestNamedPeople (all 2); test_w3_guides.TestTheOriginatorReadsTheirOwnRequest (all 3) | L18: Pass | M18: ✅ | N18: Direct test | O18: 14 | P18: Config + Build — Committee Formation Request DocType and workflow; custom Create-Forum wizard screen; build for the completeness gate. | S18: E7 | T18: 6
A19: G-18 | B19: CGF | C19: Mandatory | D19: Standardised intake fields (committee-centric) | E19: Intake Form Fields | F19: The system shall define and enforce a standardized, configurable set of intake fields, validated for completeness and aligned to the platform taxonomies, covering identifying, ownership and organisational information: forum name, forum identifier, requester, forum type, jurisdiction, parent forum, child forum(s), owning organisation (operating group), owning organisation (line of business), owning organisation (business unit), and forum sponsor. | G19: Mandatory and validated fields on Committee Formation Request: name, proposed id, requester, type, jurisdiction, parent, child forums, operating group, line of business, business units, sponsor. The fields G-17 adds are also present: new-committee flag, rationale, purpose and scope, responsibilities, delegating authority and its approval, timeline, first meeting. | H19: a | I19: (a) Portal screen | J19: Any submitted request, for example CFR-2026-00002 Operational Resilience Steering Committee. | K19: test_formation.TestIntake.test_required_fields_are_enforced_before_submission, …test_a_modify_request_must_name_its_subject, …test_one_intake_covers_create_modify_and_retire | L19: Pass | M19: ✅ | N19: Direct test | O19: 3 | P19: Config — mandatory-field and validation metadata on the intake DocType. | Q19: Δ | S19: E7 | T19: 6
A20: G-19 | B20: CGF | C20: Mandatory | D20: Forum data reused (documents, escalations, risk appetite); inbound governed; mapped, validated, traceable | E20: Integration Capabilities | F20: The system shall make forum data available for consistent reuse wherever governance context is required — approving forums for governing documents, escalation pathways, risk appetite and risk identification — and shall consume governance-relevant data from elsewhere. Data exchange shall be field-mapped, validated, and subject to defined handling rules for invalid, missing or incomplete data, and shall be traceable for audit. | G20: Reuse inside the database: Governing Document.approving_forum (listed on /forum) and Escalation Forum Link (Escalations tab on /forum). /imports (CS-11) uploads, maps, validates, reviews rows, commits or discards (importing.upload_batch, revalidate_batch, exclude_row, commit_reviewed_batch, discard_batch). Gap: the outbound export file (importing.export_records) has no caller, so no forum data file can be produced for the risk appetite or risk register. No import profile targets governance data (profiles exist for Escalation Matter and Regulatory Requirement only). External Reference rows are entered on desk. | H20: c | I20: (c) Partly reachable | J20: EXTR-00001…00004 on FRM-2026-00005 and FRM-2026-00006. IMPB-00001 (escalation import, Validated). 0 export batches. FRM-2026-00006 approves 5 governing documents. | K20: consilium_core.tests.test_import_pipeline.TestImportPipeline (all 9); consilium_core.tests.test_imports_portal.TestUpload (all 5), TestReview (all 7), TestDiscard (all 1), TestMethods (all 1); escalation.tests.test_import_export.TestImportPath (all 4) | L20: Pass | M20: ✅ | N20: Direct test | O20: 30 | P20: Config + Build — reuse by Policy and Escalation is an in-database relationship; reuse by the risk appetite system and the risk register is an export file; inbound is the manual import path. | Q20: Δ | R20: Class (c) | S20: E6, E21, E28 | T20: 13
A21: P-1 | B21: POL | C21: Mandatory | D21: Central repository with RBAC; restricted handling limits view, download, print, share | E21: Policy Repository | F21: The system shall provide a centralized, searchable repository of all governing documents and their metadata, covering at minimum Frameworks, Policies, Standards, Procedures and Supporting Documents. Access, visibility and permitted actions shall be governed by role-based access control. The system shall identify confidential or restricted documents and apply enhanced handling so that view, download, print and share are limited to authorized roles. | G21: Governing Document (5 types; Directive is deliberately not modelled); /policies, /policy and /document-view. policy/handling.py is registered in hooks.py as has_permission and permission_query_conditions on Governing Document and Document Version, plus File.before_insert (guard_file_privacy). Read is narrowed for Confidential and Restricted documents. Print, download and share are refused per flag and rendition on the print view, file fetch, share and e-mail. Loosening the handling is refused to anyone but the policy office, and the refusal is logged. | H21: a | I21: (a) Portal screen | J21: GDOC-00010 Anti-Money Laundering Policy: Confidential, with the three flags off; PPUB-00008 Targeted Groups, view-only. GDOC-00015 Artificial Intelligence Use Standard: Restricted. | K21: policy.tests.test_handling.TestVisibility (all 8), TestActions (all 7), TestHandlingChanges (all 6), TestVersionBody (all 4), TestVersionHooks (all 2), TestViewerPage (all 5); policy.tests.test_repository.TestGoverningDocument.test_confidential_closes_the_three_actions_by_default | L21: Pass | M21: ✅ | N21: Direct test | O21: 35 | P21: Config + Build — Governing Document DocType and permission rules; build for the restricted-handling controls (download/print/share gating), which are not native. | Q21: Δ | S21: E11, E30 | T21: 7
A22: P-2 | B22: POL | C22: Mandatory | D22: Advanced search and filter | E22: Search and Retrieval | F22: The system shall provide advanced search and filtering of governing documents by metadata. | G22: /policies: filters for type, phase, group, risk category, handling, owner and standing, all kept in the URL. Full-text search over title, reference, abstract, body and the current version's text goes through repository.search, which honours permissions and handling. Owner options come from repository.owners. The header's global search finds a document by reference or title from any page, through the same permission and handling rules. | H22: a | I22: (a) Portal screen | J22: /policies?standing=overdue lists GDOC-00003, GDOC-00009 and GDOC-00014, all in force and past next_review_on. | K22: policy.tests.test_wave3.TestSearch (all 4); test_repository.TestGoverningDocument.test_search_filters_and_matches_title_and_content, …test_search_respects_permissions; consilium_core.tests.test_global_search.TestGlobalSearch (all 9) | L22: Pass | M22: ✅ | N22: Direct test | O22: 17 | P22: Config + Build — as G-2. | Q22: Δ | S22: E11, E35 | T22: 10
A23: P-3 | B23: POL | C23: Mandatory | D23: Metadata tagging (named attributes, accountability roles) | E23: Policy Tagging | F23: The system shall support metadata-driven tagging using controlled fields, field dependencies and standardized taxonomies. Metadata shall include at minimum: document identifiers (name, identifier, type); ownership and accountability roles; organisational alignment; risk classification and applicability; lifecycle status and relationships. Named attributes include document name, document identifier, key contact, document type, jurisdiction, parent document, child document(s), primary risk category, legal entity, owning organisation (operating group), owning organisation (line of business), direct document link, training-required flag, attachments, document approver, document liaison, document owner, document delegate (optional), document sponsor, line of defence, material-entity flag and lifecycle phase. | G23: Every named field and child table, including the accountability-roles table. Shown on /policy, captured on the desk (DK-1), and correctable one field at a time on /policy (metadata.correct_metadata, with a reason). Retired taxonomy values are not offered (standard_queries). | H23: a | I23: (a) Portal screen | J23: GDOC-00005 Outsourcing and Third-Party Risk Policy: regulatory-required, parent GDOC-00003, approving forum FRM-2026-00006. | K23: test_repository.TestGoverningDocument.test_creates_with_required_metadata, …test_refuses_creation_without_required_metadata, …test_material_entity_flag_requires_an_entity; policy.tests.test_entities.TestAccountabilityAndReferences (all 3); policy.tests.test_wave3.TestMetadataCorrection (all 3) | L23: Pass | M23: ✅ | N23: Direct test | O23: 11 | P23: Config — Link and child-table fields against Core taxonomies; accountability roles as a child table. | Q23: Δ | S23: E3, E11 | T23: 10
A24: P-4 | B24: POL | C24: Mandatory | D24: Parent, child and addendum lineage; family dashboard | E24: Document Mapping and Parent-Child Lineage | F24: The system shall allow governing documents to be mapped to related governing documents — parent, child and addendum — and shall present document families in a dashboard view. | G24: Document Relationship plus parent_document, with cycles prevented. lineage.lineage_of is drawn on /policy, and a restricted child is not named to a reader who cannot see it. The "Document families" section on /reports (reporting.families) is permission-filtered and exports to CSV. | H24: a | I24: (a) Portal screen | J24: GDOC-00001 ERM Framework → GDOC-00002, 00003, 00006. GDOC-00003 → 00005, 00007, 00012. GDOC-00008 → 00011. GDOC-00013 (retired) → 00014. | K24: test_repository.TestLineage (all 4); policy.tests.test_wave3.TestLineageVisibility (all 1), TestReporting (all 3) | L24: Pass | M24: ✅ | N24: Direct test | O24: 9 | P24: Config + Build — Document Relationship child table; build for the family/lineage visualisation. | S24: E11, E33 | T24: 6
A25: P-5 | B25: POL | C25: Mandatory | D25: Links to risk-programme objects (forums, risks, controls, training, issues) | E25: Mapping to Risk Programmes | F25: The system shall allow governing documents to be linked to other risk programme objects: risk assessments; processes, risks and controls; training; a regulatory-requirement indicator; and related issues. | G25: In the database: approving_forum, shown on /policy and resolved from /forum; the regulatory-required indicator and references; the training-required flag; the violation → escalation link. The Impact panel on /policy (ai/impact.py) walks the forums, regulation, monitoring and violations. Gap: foreign risks, controls, processes and training items are External Reference rows (or Implementation Plan impacted processes and controls) entered on the desk only. /policy does not show them, and no import profile brings them in for documents. | H25: c | I25: (c) Partly reachable | J25: GDOC-00003 approved by FRM-2026-00006. The 6 External Reference rows on the site are all on forums and escalations; none is on a governing document. | K25: consilium_core.tests.test_ai_features.TestImpact.test_the_rule_based_impact_reaches_lineage_regulation_forums_monitoring_and_violations; policy.tests.test_entities.TestImplementationPlan.test_working_groups_and_references_are_multi_valued | L25: Pass (qualified) | M25: ✅ (in-database links; nothing tests external references on a document's page) | N25: Direct test | O25: 4 | P25: Config + Build — in-platform links where the counterpart is a Consilium record (governance forums, escalations); external references held as imported reference records, not live links. | Q25: Δ | R25: Class (c), No direct test | S25: E12 | T25: 6
A26: P-6 | B26: POL | C26: Mandatory | D26: Regulatory-required with dependent capture; keep references current; notify owners on regulatory change | E26: Regulatory Linkage | F26: The system shall allow a governing document to be designated regulatory-required, and when so designated shall require capture of the relevant regulatory detail through dependent fields. It shall maintain linkage from documents to the applicable laws, rules, regulations or standards, keep references and effective dates current, and notify impacted document owners when a tracked regulatory change occurs. | G26: The flag plus Document Regulatory Reference, shown on /policy. A regulatory-change file is imported on /imports through the seeded profile IMPP-00001 (policy/regulatory_import.py, whose prepare_changes makes a blank cell mean "unchanged"). A change can also be recorded on /regulatory-updates. Either way the Regulatory Requirement controller (notify_citing_owners) tells the owners of citing documents and forums through the templated event regulatory.requirement.changed. | H26: a | I26: (a) Portal screen | J26: 12 requirements. The dispatch "Regulatory change: Operational Resilience Guideline…" went by e-mail to the owner of GDOC-00007. IMPP-00001 is seeded, but no regulatory batch has been run on the demo. | K26: consilium_core.tests.test_regulatory_change.TestRegulatoryChangeFanOut (all 6); policy.tests.test_wave3.TestRegulatoryChangeImport (all 2); consilium_core.tests.test_ai_features.TestRegulatory (all 8); test_repository.TestGoverningDocument.test_regulatory_flag_requires_a_reference | L26: Pass | M26: ✅ | N26: Direct test | O26: 20 | P26: Config + Build — dependent Regulatory Reference child table; regulatory-change intake is an imported file, and the impact-notification fan-out is a build. | Q26: Δ | S26: E12, E29 | T26: 9
A27: P-7 | B27: POL | C27: Mandatory | D27: Configurable lifecycle workflows by type and change; SLA per step; approaching or breached alerts | E27: Configurable Automated Workflow | F27: The system shall support administratively configurable automated workflows for every stage of the document lifecycle, varying by document type and type of change, with conditional routing, tracking and reporting of service levels for all lifecycle steps, and alerts for approaching or breached thresholds. Configuration shall require no custom development. | G27: The framework Workflow Governing Document Lifecycle and Document Lifecycle Gate rows are configured on the desk (DK-4). Conditional routing by type, change and risk comes from Approval Route. A new workflow state needs no schema change (derive_phase_from_state and the Workflow State Flag phase column, opt-in per site). Status-driven SLA clocks per lifecycle step (sla.on_subject_update) and the daily and hourly sla.sweep send the warning (warning_threshold_pct) and the breach through templates. Actions are taken on /policy. Note: step SLAs are seeded for Review and Approved only; other phases need an SLA Definition row. | H27: a | I27: (a) Portal screen | J27: POL-STEP-REVIEW is running on GDOC-00005, 00011 and 00015; POL-STEP-APPROVED on GDOC-00006. The intake clocks POL-INTAKE-MAJOR and MINOR are Met on PINT-00001…03 and Running on PINT-00004 and 00008. | K27: policy.tests.test_lifecycle.TestLifecycleConfiguration (all 5), TestApprovalRouting (all 7); policy.tests.test_w3_state_phase.TestDerivedPhase (all 7); consilium_core.tests.test_sla_measures.TestGoverningDocumentSteps (all 1), TestWarningsAndBreaches (all 7); policy.tests.test_intake.TestClassificationDrivesRoutingAndService (all 5) | L27: Pass | M27: ✅ | N27: Direct test | O27: 36 | P27: Native + Config + Build — native workflow engine; build for the service-level definition, clock and breach alerting. | S27: E12, E29 | T27: 9
A28: P-8 | B28: POL | C28: Mandatory | D28: Multi-step approval: parent-owner approval, reminders, exceptions and exemptions, group routing, annual attestation, horizon-scan scheduling | E28: Configurable Review and Approval Workflow | F28: The system shall support a multi-step approval process across stakeholders and roles, sequential or parallel, including: approval by parent-document owners of changes to child documents where required; automated routing, reminders and escalations; real-time approval tracking with timestamps, comments and sign-offs; forms and workflows for exception requests and exemptions; routing of approvals and notifications to user groups; role-based assignment of approval steps; conditional approval paths by document type, change type or risk level; a full audit trail of approval actions; routing of annual attestation notices and deadline reminders; and horizon-scanning notifications — notifying owners when scans are due, tracking completion of manual scans, and triggering downstream workflow after a scan. | G28: These parts are built: route resolution with a parent-owner step (routing.resolved_steps); steps raised, decided (assignee or live delegate) and bypassed only under an exception authorisation, all from /policy; sequential order enforced; steps in /tasks. Gate exceptions are requested by the owner and approved by the policy office. Exemptions are on the desk, with a daily lapse. Document attestation campaigns are opened from /policy (attestation.open_campaign), with reminders on the campaign schedule and answers in /tasks. Horizon scans are recorded from /policy, chased by daily horizon.remind_due, and a triggering scan opens a review cycle. Missing: (1) reminders and escalation for an approval step left pending. No job reads open Approval Decision rows. The lifecycle-phase SLA warns only the document owner, because sla.RESPONSIBLE_FIELDS names no approver. (2) Routing approvals to user groups. A step resolves to one user from a document field or a named user. required_role is stored but is not used as a queue for policy steps, unlike formation. | H28: d | I28: (d) Not implemented (whole or mandatory part) | J28: GDOC-00005 in Review: 1 step approved, 1 pending. GDOC-00006 Model Risk Management Policy: 3 approved decisions. ACAM-00004: 5 attested, 4 pending. PHSC-00002 → PRVC-00001, review triggered. PEXM-00001 authorised exemption. | K28: policy.tests.test_portal_actions.TestApprovalChain (all 15); test_lifecycle.TestApprovalRouting (all 7), TestParentOwnerApproval (all 3); consilium_core.tests.test_core_controls_wave3.TestSequentialApprovals (all 6); policy.tests.test_wave3.TestGateExceptions (all 4), TestAttestationCampaign (all 2); policy.tests.test_horizon.TestScanCadence (all 8), TestScanTriggersReview (all 5); test_entities.TestExemptionLifecycle (all 5); consilium_core.tests.test_w3_guides_core.TestCampaignReminderSchedule (all 4) | L28: Pass (qualified) | M28: ✅ (what exists; nothing tests approval reminders because there are none) | N28: Direct test | O28: 64 | P28: Config + Build — workflow configuration; build for parent-owner approval injection, attestation campaign integration and horizon-scan scheduling. | Q28: Δ | R28: Class (d), No direct test | S28: E12, E14, E18, E27 | T28: 26
A29: P-9 | B29: POL | C29: Mandatory | D29: Full history; prior versions accessible; revert | E29: Version Control, Audit History and Accountability | F29: The system shall track every change to a governing document, maintain a complete history, and log every user action with timestamp and attributed actor. Prior versions shall be archived and remain accessible. The system shall additionally allow an authorised user to revert a document to a previous version. | G29: Native Version log (track_changes), shown as the change log on /policy. Body version chain in Document Version. Upload goes through publication.upload_new_version (text or a file attached privately) and revert through publication.revert_version (required reason, forward-only). Both are on /policy, and a revert keeps the lifecycle phase. Prior versions open in /document-view. | H29: a | I29: (a) Portal screen | J29: 157 document versions; GDOC-00001, 00004, 00005 and 00015 have 2 versions each. No document revert has been done on the demo; the one Version Revert Log row is on forum FRM-2026-00010. | K29: policy.tests.test_portal_actions.TestVersions (all 9); policy.tests.test_wave3_policy.TestRevertLeavesTheLifecycleAlone (all 1); test_lifecycle.TestVersioningAndPublication.test_revert_writes_a_new_version_and_never_rewrites_one; consilium_core.tests.test_versioning.TestVersioning (all 9) | L29: Pass | M29: ✅ | N29: Direct test | O29: 23 | P29: Native + Build — native field-level version log for metadata; document body versions and revert are a build, because we hold the authoritative body. | Q29: Δ | S29: E4, E27 | T29: 16
A30: P-10 | B30: POL | C30: Mandatory | D30: Periodic review: schedule, notify when due to begin and when due, SLA on overdue, outcomes | E30: Policy Maintenance | F30: The system shall support periodic reviews through scheduling, notification when a review is due to begin and when due, service-level tracking of overdue reviews, and documentation of review outcomes. | G30: Review cycles are opened and concluded with an outcome on /policy (horizon.open_review and conclude_review). The daily reminders.daily sends policy.review_cycle.starting, …due_soon, …overdue and …escalated, and policy.review.due_soon, …overdue and …escalated for documents with no cycle open. Reminder Log de-duplicates. SLA POL-REVIEW-CYCLE times a cycle that is underway. "Policy reviews due" appears in /tasks. | H30: a | I30: (a) Portal screen | J30: GDOC-00003 overdue: RMDL-00001 overdue, RMDL-00002 escalated. PRVC-00005 overdue and escalated (RMDL-00003 and 00004), and its SLA clock Breached. PRVC-00004 concluded "Minor Update". | K30: consilium_core.tests.test_reminders.TestDocumentReviewReminders (all 9); policy.tests.test_portal_actions.TestReviewsAndScans (all 7); test_entities.TestReviewCycle (all 4); test_repository.TestGoverningDocument.test_review_date_derives_from_cadence | L30: Pass | M30: ✅ | N30: Direct test | O30: 23 | P30: Config + Build — Document Review Cycle record; scheduled job; build for the service-level clock. | S30: E29 | T30: 3
A31: P-11 | B31: POL | C31: Mandatory | D31: Monitoring: define, schedule, notify when due, log results, dashboard | E31: Monitoring and Control Activities | F31: The system shall allow monitoring activities to be defined, scheduled, tracked and reported per governing document; send notifications when they fall due; log their results; present a dashboard of monitoring outcomes for the enterprise policy office; and maintain auditable records. | G31: Monitoring Activity is defined on the desk. Results are recorded on /policy (monitoring.record_result, which moves next_due_on forward). The daily reminders.remind_monitoring sends due soon, overdue and escalated to the document owner. The "Monitoring outcomes" section on /reports exports to CSV. | H31: a | I31: (a) Portal screen | J31: PMON-00001 due 2026-08-15 is overdue and was chased (RMDL-00006, escalated RMDL-00007). PMON-00003 was chased too (RMDL-00008 and 00009). 10 results; PMRS-00003 Not Effective → PVIO-00002. | K31: policy.tests.test_monitoring.TestMonitoring (all 4); policy.tests.test_portal_actions.TestMonitoring (all 8); consilium_core.tests.test_reminders.TestMonitoringReminders (all 2); policy.tests.test_wave3.TestReporting (all 3) | L31: Pass | M31: ✅ | N31: Direct test | O31: 21 | P31: Config + Build — Monitoring Activity and Monitoring Result DocTypes; scheduled job; dashboard. | S31: E15, E29 | T31: 8
A32: P-12 | B32: POL | C32: Mandatory | D32: Policy reporting: status, lifecycle, coverage; drill-down; families, reviews, monitoring, exceptions, violations; export | E32: Reporting and Dashboards | F32: The system shall provide reporting and dashboards for oversight of policy governance enterprise-wide, showing status, lifecycle progression, compliance, coverage and performance. Reporting shall support filtering, aggregation and drill-down by document type, lifecycle status, ownership, risk category, legal entity, applicability, review status and service-level performance. Dashboards shall present current and historical views including document families, parent-child relationships, upcoming and overdue reviews, monitoring outcomes, exceptions and violations, with export for management, audit and regulatory needs. | G32: The /reports documents section counts by phase, type, group and handling. Upcoming, overdue and no-review counts drill into /policies?standing=…. Missing metadata is listed. Families, monitoring outcomes, open violations by severity, exceptions, and review and retirement dispositions come from reporting.policy_sections, all over what the viewer may read, each with CSV export. SLA clocks are counted by DocType. Gap: drill-down by legal entity and applicability exists only through the desk report builder (DK-5, named in the trace), not on /policies. | H32: a | I32: (a) Portal screen | J32: 15 documents across Draft, Review, Approved, Published, Implemented and Retired; 5 violations; 13 dispositions (PDSP-00001…13). | K32: policy.tests.test_wave3.TestReporting (all 3); consilium_core.tests.test_portal_pages.TestEveryPageIsCovered (all 1) | L32: Pass (qualified) | M32: ✅ (sections and export; the browser-side counts are covered only by the page-render tests) | N32: Direct test | O32: 6 | P32: Native + Build — as G-12. | R32: No direct test | S32: E20, E33 | T32: 6
A33: P-13 | B33: POL | C33: Mandatory | D33: RBAC, segregation of duties, delegation; restricted-document controls; access changes logged | E33: Role-Based Access Control | F33: The system shall restrict access to documents, data and actions by defined role, responsibility and delegated authority, enforcing segregation of duties over creation, editing, review, approval, monitoring, reporting, upload and publication. Roles shall be configurable and shall include Policy Owner, Reviewer, Approver, Viewer, Administrator and organisational groupings. Delegation shall be supported with accountability and auditability. Enhanced controls shall apply to confidential and restricted documents, limiting view, download, print and share to authorized users. All access assignments, changes and actions shall be logged. | G33: Roles are enforced server-side (DK-2). lifecycle.authorise applies segregation of duties per action: no one bypasses their own step or approves their own gate exception. Authority Delegation is kept, with a daily refresh. Restricted-document gating is in policy/handling.py (see P-1). Refused loosening is logged, and change tracking is on. | H33: a | I33: (a) Portal screen | J33: GDOC-00015 Restricted; GDOC-00010 Confidential; 4 delegations (ADEL-00001…04). | K33: test_repository.TestGoverningDocument.test_a_reviewer_cannot_create_a_document, …test_a_policy_owner_cannot_delete_a_document, …test_the_policy_office_may_delete_a_document, …test_an_auditor_may_read_but_not_write; policy.tests.test_handling.TestVisibility (all 8), TestHandlingChanges (all 6); consilium_core.tests.test_delegation.TestDelegation (all 13); policy.tests.test_wave3.TestGateExceptions.test_nobody_approves_their_own_request | L33: Pass | M33: ✅ | N33: Direct test | O33: 35 | P33: Native + Config + Build — native role, permission-level and row-level permission engine; build for restricted-document action gating and the delegation register. | Q33: Δ | S33: E2, E30 | T33: 7
A34: P-14 | B34: POL | C34: Mandatory | D34: Notifications across the lifecycle; templates with dynamic fields; email and in-app; conditional triggers | E34: Notifications | F34: The system shall send configurable, templated, automated notifications across every lifecycle stage — drafting comments and revisions, review, approval, publication, and maintenance activities including monitoring, annual assessments and periodic reviews — with templates carrying dynamic fields, multiple delivery channels (email, in-application) and conditional triggers on events, deadlines and service-level breaches. | G34: Notification Template (49 events, editable per channel on the desk, rendered in a Jinja sandbox) goes through notification.notify. There are e-mail (SMTP through the framework mail queue, or Microsoft Graph; hourly retry), in-app and record channels. Policy events: review and review-cycle due, starting, overdue and escalated; monitoring due, overdue and escalated; audience on publish, change and retire; review disposition (return with comments, accept); gate exception approved; attestation opened; horizon scan due; SLA warning and breach; regulatory change; approval step requested, decided and bypassed (policy.approval.requested, policy.approval.decided, policy.approval.bypassed, raised by policy/routing.py and seeded on migrate). Templates and channels are configured on the desk (DK-7) and events are raised by hooks and jobs (BG), as the trace names. The approver is also shown the step in /tasks. | H34: b | I34: (b) Desk / config / job by design | J34: 79 e-mail dispatches on Governing Document subjects, for example "Review Accepted: …", "Retired: Vendor Management Standard (GDOC-00013)", "Escalated: review of Operational Risk Ma…". | K34: consilium_core.tests.test_notification_templates.TestEventApi (all 10), TestSeeding (all 2); policy.tests.test_wave3_policy.TestAudienceNotice (all 1); policy.tests.test_wave3.TestChangeAndRetirement (all 6), TestReviewerReturn.test_a_reviewer_returns_with_comments_and_the_owner_is_told; consilium_core.tests.test_reminders.TestDocumentReviewReminders (all 9); policy.tests.test_portal_actions.TestApprovalChain (all 15, including the approver being told when steps are raised); consilium_core.tests.test_graph_mail.TestTheDispatchRecord (all 7) | L34: Pass | M34: ✅ | N34: Direct test | O34: 57 | P34: Native + Config + Build — as G-14. | Q34: Δ | S34: E19, E29, E36 | T34: 12
A35: P-15 | B35: POL | C35: Mandatory | D35: Templates per type and action; cover metadata; enforce naming conventions and required fields | E35: Document Templates | F35: The system shall allow templates to be created and configured per document type and per action (new, edit, retire, review), aligned to the corporate format including a cover page carrying required metadata, predefined sections and formatting. New document types and templates shall be creatable without custom development. Templates shall enforce standardized naming conventions and required fields, and shall carry hyperlinks to related documents and regulatory references. Collaboration for real-time feedback, revision, redlining and version comparison during drafting and review is provided by the external document editor. | G35: Document Template with sections, template file, required_fields (feeding the "Required Metadata Complete" gate) and the naming pattern, per type and action, on the desk (DK-1). policy/naming.py checks the name against the active New template's pattern on every save (desk, REST, portal) and at intake classification. The message gives the expected form. The template file and sections are not offered on the portal. | H35: b | I35: (b) Desk / config / job by design | J35: 5 templates, for example "Policy — new issue" with pattern <Subject> Policy. | K35: policy.tests.test_naming_glossary.TestNamingPattern (all 1), TestNamingEnforcement (all 7); policy.tests.test_entities.TestDocumentTemplate (all 4) | L35: Pass | M35: ✅ | N35: Direct test | O35: 14 | P35: Config + Build — Document Template DocType; build for naming-convention enforcement. Collaborative drafting is out of scope here. | Q35: Δ | S35: E30 | T35: 2
A36: P-16 | B36: POL | C36: Mandatory | D36: Intake form; dynamic question set classifies major or minor, driving routing and SLA; trace retained | E36: Intake Templates and Change Classification | F36: The system shall provide a configurable intake form for requests to create, change or retire a governing document. For a change to an existing document the system shall present a dynamic set of questions whose answers determine whether the change is major or minor, and that classification shall drive approval requirements, review steps, service levels and escalation paths. The system shall enforce required fields and naming conventions, and shall retain version history and the rationale for each classification, with a full audit trail of intake submissions, classification logic applied and workflow actions taken. | G36: The /policy-intake screen raises the request, answers the rule set's questions (dependent questions shown), classifies (intake.classify_request) and shows the rule that fired with its trace. The requester challenges; the policy office overrides with a justification (original kept) and creates the document. Withdrawal is recorded with a reason. The Core rules engine is versioned and sealed. Classification selects the route and starts the SLA clock. Naming is checked at intake. | H36: a | I36: (a) Portal screen | J36: PINT-00001 → CASS-00001 Major (R10) → GDOC-00006. PINT-00002 → CASS-00002 Minor (R20) → GDOC-00011. PINT-00008 classified on the portal as CASS-00005 Minor. Rule set CRS-00001 v1.0. | K36: policy.tests.test_portal_actions.TestIntake (all 12), TestPages.test_the_intake_page_renders; policy.tests.test_intake.TestClassification (all 10), TestIntakeRequest (all 4), TestClassificationDrivesRoutingAndService (all 5); consilium_core.tests.test_classification.TestClassification (all 16) | L36: Pass | M36: ✅ | N36: Direct test | O36: 51 | P36: Build — an admin-configured rules engine: question sets, answer options, rules and resulting classification, evaluated at submission and recorded with the evaluation trace. | Q36: Δ | S36: E13, E27 | T36: 16
A37: P-17 | B37: POL | C37: Mandatory | D37: Attach any documents; audit log | E37: Document Management | F37: The system shall allow documents to be attached with no limitation on type or number, and shall present an audit log of all activity. | G37: Native attachments (desk, DK-6); body files uploaded from /policy are attached privately. The change log is on /policy. record_history (changes, comments and notifications) and the evidence-pack ZIP with a SHA-256 manifest come from evidence.export_pack on /policy. | H37: b | I37: (b) Desk / config / job by design | J37: 55 Version rows and 47 comments on governing documents; 1 file attachment. | K37: test_repository.TestGoverningDocument.test_update_is_tracked; policy.tests.test_handling.TestActions.test_an_attached_file_follows_the_download_flag_and_the_owner_may_always_download; policy.tests.test_portal_actions.TestVersions.test_a_file_attached_to_the_document_becomes_a_version; consilium_core.tests.test_core_controls_wave3.TestHistoryAndEvidencePack (all 4) | L37: Pass (qualified) | M37: ✅ (tracking switched on; the framework writes no Version rows under test) | N37: Direct test | O37: 10 | P37: Native — native attachment and activity log. | R37: No direct test | S37: E5 | T37: 5
A38: P-18 | B38: POL | C38: Mandatory | D38: Retention and WORM | E38: Data and Document Retention | F38: The system shall retain data and documents in accordance with the applicable retention policy and requirements, and shall hold documents and data in a write-once, read-many form for the duration of their retention period. | G38: Core retention guards (wildcard before_validate and on_trash), legal hold, and daily retention.flag_due_for_disposal, which raises a Disposition Event awaiting approval and deletes nothing. A retired document records its retention position in Document Disposition. Gap: executing a disposal (retention.execute_disposition) has no caller outside tests, so it is reachable from code only. Retention Assignment and Legal Hold are desk records. | H38: c | I38: (c) Partly reachable | J38: All 15 documents carry retention_class POL-DOCUMENT, but there are 0 Retention Assignments, 0 Legal Holds and 0 Disposition Events on the demo. PDSP-00013 records GDOC-00013's retirement. | K38: consilium_core.tests.test_retention.TestRetention (all 14); consilium_core.tests.test_core_controls_wave3.TestScheduledDisposalReview (all 5) | L38: Pass | M38: ✅ | N38: Direct test | O38: 21 | P38: Build — as G-16. | Q38: Δ | R38: Class (c) | S38: E5 | T38: 5
A39: P-19 | B39: POL | C39: Mandatory | D39: Publish to audiences with view-only, print or download renditions; retain retired and superseded | E39: Publication | F39: The system shall publish governing documents with controlled access — general population, restricted, or targeted groups — supporting view-only, print-enabled and downloadable renditions according to role-based permission. Retired and superseded documents shall be retained with their version history. | G39: /policy Publish: publication.audience_preview first, then publish_record (All Employees, restricted or targeted groups; rendition flags), and withdraw_publication. The audience is told through policy.document.audience. Renditions are enforced by handling.rendition on print, download and /document-view. Retired and superseded documents keep their chain. | H39: a | I39: (a) Portal screen | J39: PPUB-00008: GDOC-00010, Targeted Groups, view-only. GDOC-00013 Vendor Management Standard: Retired, superseded by GDOC-00005, 11 publications. | K39: policy.tests.test_portal_actions.TestPublication (all 7); policy.tests.test_handling.TestActions.test_a_view_only_rendition_closes_download_even_when_the_document_allows_it; test_lifecycle.TestVersioningAndPublication.test_a_view_only_rendition_closes_print_and_download | L39: Pass | M39: ✅ | N39: Direct test | O39: 11 | P39: Build — Document Publication record carrying audience and permitted renditions; build for the rendition-permission gate. | S39: E27, E30 | T39: 14
A40: P-20 | B40: POL | C40: Mandatory | D40: Governed exchange: mapped, validated, handling rules, traceable | E40: Integration Capabilities | F40: The system shall exchange policy data consistently with enterprise risk, governance and related platforms, keeping policy information, metadata and relationships aligned with authoritative sources. Inbound and outbound exchanges shall be field-mapped and configurable for source/target compatibility; alignment to enterprise taxonomies (organisational hierarchy, primary risk category, material entity) shall be maintained; handling rules shall be defined for invalid, missing or incomplete data; integration methods and frequency shall be configurable; exchanges shall support enterprise records management and retention, and enterprise identity for user selection, organisational alignment and notification routing; inbound and outbound data shall be validated for completeness and integrity; and all integration activity shall be traceable for audit and compliance. | G40: Inbound goes through /imports (CS-11): upload with a hash, mapping, validation, per-row review, exclude, revalidate, commit and discard, all batch-logged. Gap: the governed outbound export (importing.export_records, which writes an Export Batch) has no caller outside tests. Policy data leaves only as the /reports CSV (reporting.export, not batch-logged or mapped) or through desk report export. No import profile targets Governing Document. | H40: c | I40: (c) Partly reachable | J40: IMPP-00001 Regulatory changes (seeded); IMPB-00001 is an escalation batch. No policy-document batch and no Export Batch. | K40: consilium_core.tests.test_import_pipeline.TestImportPipeline (all 9); consilium_core.tests.test_imports_portal.TestUpload (all 5), TestReview (all 7), TestDiscard (all 1), TestMethods (all 1); policy.tests.test_wave3.TestRegulatoryChangeImport (all 2) | L40: Pass | M40: ✅ | N40: Direct test | O40: 28 | P40: Build — the manual/file import and export service, with mapping, validation, handling rules and a traceable batch log. Identity alignment is satisfied by app-native users with pluggable single sign-on. | Q40: Δ | R40: Class (c) | S40: E21, E28 | T40: 7
A41: P-21 | B41: POL | C41: Mandatory | D41: Applicability and exemptions; notify applicable parties on create, change, retire | E41: Applicability Management | F41: The system shall maintain applicability for each governing document and notify applicable parties automatically when a document is created, changed or retired. Applicability shall cover business units, subsidiaries and material entities; jurisdictions at provincial, federal and international level; roles or functions responsible for compliance; and formal exemptions and deviations with their approvals. | G41: Document Applicability and Applicability Exemption are captured on the desk and shown on /policy, with a daily lapse of expired exemptions. The audience is resolved at the time (applicability.affected_parties), and the publish panel previews it. First publication raises policy.document.audience; a new version in force raises policy.document.changed and retirement policy.document.retired (disposition.py, from on_update). | H41: a | I41: (a) Portal screen | J41: GDOC-00010: PEXM-00001 authorised Legal Entity exemption; PEXM-00002 deviation requested on GDOC-00004. Retirement notice sent for GDOC-00013. | K41: test_repository.TestApplicability (all 8); test_entities.TestExemptionLifecycle (all 5); policy.tests.test_wave3.TestChangeAndRetirement (all 6); policy.tests.test_portal_actions.TestPublication.test_the_office_records_a_publication_and_the_audience_is_told | L41: Pass | M41: ✅ | N41: Direct test | O41: 22 | P41: Config + Build — Document Applicability child table and Applicability Exemption DocType; build for the notification fan-out to the resolved audience. | S41: E11 | T41: 5
A42: P-22 | B42: POL | C42: Mandatory | D42: Violations captured, linkable to an external issue, auditable, reportable | E42: Violation and Issue Management | F42: The system shall capture policy violations — document reference, violation type, date, responsible party and corrective actions — and shall support linking a logged violation to an external issue-management record. All violations shall maintain an audit trail and be reportable for compliance monitoring and governance. | G42: Policy Violation is logged and moved on from /policy (monitoring.log_violation and update_violation). The controller refuses reopening, and refuses closing without a note. Violations appear on /policy and under "Open violations" on /reports, with CSV export. The external issue link (external_reference) and the escalation link are set on the desk (DK-1, named in the trace). | H42: a | I42: (a) Portal screen | J42: PVIO-00001 High on GDOC-00012 → ESC-2026-00009. PVIO-00002 on GDOC-00010 → ESC-2026-00003. | K42: policy.tests.test_monitoring.TestViolations (all 5); policy.tests.test_wave3.TestViolationTransitions (all 3), TestReporting (all 3); policy.tests.test_portal_actions.TestMonitoring.test_a_reviewer_logs_a_violation | L42: Pass | M42: ✅ | N42: Direct test | O42: 15 | P42: Config + Build — Policy Violation DocType; the external issue link is stored as a reference identifier plus an import/export mapping, not a live connector. | Q42: Δ | S42: E15, E33 | T42: 6
A43: P-23 | B43: POL | C43: Mandatory | D43: Detect metadata left invalid (retired parent) and require realignment | E43: Metadata Integrity Maintenance | F43: The system shall allow document owners and the enterprise policy office to identify changes that leave required fields invalid — for example, where a required parent document is retired, the child document shall be notified and its owner required to realign to a new parent. | G43: on_update raises a Metadata Remediation Task when a parent leaves force. The task appears in /tasks under "Metadata to correct" and is corrected in place on /policy (metadata.correct_metadata, which resolves the task). /reports lists missing metadata with a "Correct in place" link. | H43: a | I43: (a) Portal screen | J43: GDOC-00013 retired → PMRT-00001 on GDOC-00014 (parent_document, "Parent Retired"). | K43: policy.tests.test_monitoring.TestMetadataMaintenance (all 7); policy.tests.test_wave3.TestMetadataCorrection (all 3); policy.tests.test_regressions.TestReopening.test_reopening_a_parent_does_not_tell_its_children_their_parent_retired, …test_retiring_a_parent_still_tells_its_children, TestMaintenanceView (all 1) | L43: Pass | M43: ✅ | N43: Direct test | O43: 16 | P43: Build — referential-consequence detection on lifecycle transitions, raising a remediation task. | S43: E15, E28 | T43: 8
A44: P-24 | B44: POL | C44: Mandatory | D44: Glossary at enterprise and document level; prevent use of terms not in the approved glossary; linkable; versioned | E44: Glossary Management | F44: The system shall maintain a glossary of terms at enterprise level and at lower levels such as document or document-family level. It shall enforce the use of official definitions by preventing users from creating or applying terms not in the approved glossary. Terms shall be linkable to documents for contextual help. All glossary changes shall carry version control and a complete audit trail. | G44: Glossary Term sits on the Core version chain (desk). The enforcement validator refuses and logs a synonym or retired wording used instead of an enforced term, on save and on version upload. Definitions are shown in context on /policy and /document-view (glossary.in_context). Document-scoped terms are supported. Note: enforcement works through the synonyms and retired wording recorded against enforced terms; text that is in no glossary at all cannot be detected. | H44: a | I44: (a) Portal screen | J44: 13 terms; GTRM-00012 "Emergency Change" scoped to GDOC-00012 and enforced; GTRM-00011 Proposed. | K44: policy.tests.test_naming_glossary.TestGlossaryEnforcement (all 9); policy.tests.test_wave3.TestGlossaryOnThePage (all 2); policy.tests.test_monitoring.TestGlossary (all 8) | L44: Pass | M44: ✅ | N44: Direct test | O44: 22 | P44: Config + Build — Glossary Term DocType; build for the enforcement validator and the term-to-document linkage. | S44: E15, E30 | T44: 7
A45: P-25 | B45: POL | C45: Mandatory | D45: No publication without the complete approval set; bypass only with a documented exception | E45: Approval Management | F45: The system shall enforce a mandatory approval control before any governing document is published. No document may be published without completing all approvals required for its classification — new, major revision or minor revision. The approval workflow shall be configurable for multiple steps and roles, sequential or parallel, and shall keep a full audit trail of approvals including timestamp, approver identity and decision. Bypass or override without documented exception authorisation shall be prevented. | G45: Gates (Complete Approval Chain on Approved and Published; Current Version; Applicability; Publication Record) run from GoverningDocument.validate on every route. /policy shows the failing gate before an action is taken and refuses it after. Sequential order is enforced by Core. A bypass or gate exception needs an Exception Authorisation approved by the policy office, never self-approved. Record Approval needs a complete chain. | H45: a | I45: (a) Portal screen | J45: GDOC-00005 in Review: 1 approved and 1 pending step. GDOC-00011 in Review: 1 pending. Gates PLGT-00001…06. | K45: test_lifecycle.TestPublicationRefusal (all 7); policy.tests.test_regressions.TestGatesOnEveryRoute (all 3); policy.tests.test_w3_record_approval.TestRecordApprovalChecksTheChain (all 5); policy.tests.test_wave3.TestGateExceptions (all 4); policy.tests.test_portal_actions.TestLifecycleActions (all 8); policy.tests.test_wave3_policy.TestDocumentStepOrder (all 1) | L45: Pass | M45: ✅ | N45: Direct test | O45: 33 | P45: Config + Build — workflow gate on the publish transition; build for the classification-to-approval-set resolution and the exception-authorisation record. | S45: E12, E30 | T45: 8
A46: P-26 | B46: POL | C46: Mandatory | D46: Structured review: review stage, reviewer assignment, disposition with notification, version chain (editing is external) | E46: Structured Editing and Review | F46: The system shall support a structured editing and review capability: transition of a document into a designated review stage; reviewer assignment configurable by role, group or document characteristic; sequential or parallel review; inline comment and revision suggestion; owner disposition of feedback in real time with automatic notification to the originator; version control with visibility of all changes; a complete audit trail of comments, dispositions, edits and notifications; and retention of prior versions. | G46: The review stage is reached through "Submit for Review" on /policy. The reviewer returns with comments ("Return to Drafting") on /policy, cannot edit the content, and the owner is told. Reviewers and approvers are assigned by role (workflow) and by document characteristic (Approval Route), sequential or parallel. A Document Disposition is written per review round, "Review Returned" or "Review Accepted", and the originator is told (policy.review.disposition). Version chain as in P-9. Gap: a reviewer cannot take "Return to Drafting" from the desk. The Review state is editable only by the owner, so the desk's workflow action fails for the reviewer; the portal works. No assignment by user group. | H46: a | I46: (a) Portal screen | J46: PDSP-00001…12 Review Accepted (one per published document); GDOC-00005, 00011 and 00015 in Review. There is no "Review Returned" disposition on the demo. | K46: policy.tests.test_wave3.TestReviewerReturn (all 4); policy.tests.test_portal_actions.TestLifecycleActions.test_a_reviewer_returns_a_document_to_drafting; test_lifecycle.TestLifecycleTransitions (all 4) | L46: Pass | M46: ✅ | N46: Direct test | O46: 11 | P46: Build (partial) + external — inline commenting, revision suggestion and collaborative editing belong to the external document editor. Ours: the review-stage transition, reviewer assignment, the disposition record and its notification, the authoritative version chain, and retention of prior versions. | Q46: Δ | S46: E27, E33 | T46: 13
A47: E-1 | B47: ESC | C47: Mandatory | D47: Escalation repository with RBAC | E47: Escalation Repository | F47: The system shall provide a centralized, searchable repository of escalation matters and their metadata, with access, visibility and permitted actions governed by role-based access control. | G47: Escalation Matter with role permissions and the sensitivity hooks; register /escalations, detail /escalation, created on /raise-escalation (templates.raise_escalation) or the desk. | H47: a | I47: (a) Portal screen | J47: 15 matters ESC-2026-00001 … 00015 across all six states. | K47: escalation.tests.test_entities.TestEscalationMatter (all 8), escalation.tests.test_entities.TestModuleShape (all 3), escalation.tests.test_portal_actions.TestRaise (all 6) | L47: Pass | M47: ✅ | N47: Direct test | O47: 20 | P47: Config — Escalation Matter DocType plus permission rules. | S47: E16 | T47: 4
A48: E-2 | B48: ESC | C48: Mandatory | D48: Advanced search and filter | E48: Search and Retrieval | F48: The system shall provide advanced search and filtering of escalation matters by metadata. | G48: /escalations: filters on standing, age band, severity, status, type, level; free-text search on title, reference, trigger; sortable columns incl. risk types and accountable executive; filters kept in the address; search also taken from ?q=; rows read over REST so sensitive rows are excluded; Export CSV. The header's global search finds a matter by reference, title or external reference from any page, sensitive matters only for the cleared. | H48: a | I48: (a) Portal screen | J48: /escalations?standing=all&severity=High lists ESC-2026-00001, 00003, 00004, 00007, 00009, 00014, 00015 (00003 and 00004 only to cleared readers). | K48: consilium_core.tests.test_global_search.TestGlobalSearch (all 9), including …test_a_sensitive_matter_reaches_only_the_cleared and …test_a_reference_finds_the_record_but_not_a_hidden_one; scripts/browser_journeys.py journeys escalation-filters and global-search (11/11 pass); escalation.tests.test_sensitivity.TestSensitiveMatters.test_the_api_list_hides_a_sensitive_matter, …test_a_filtered_api_read_cannot_be_used_to_confirm_existence; page render consilium_core.tests.test_portal_pages.TestAdministrator.test_every_page_renders_with_its_key_sections | L48: Pass | M48: ✅ | N48: Direct test | O48: 17 | P48: Config + Build — as G-2. | Q48: Δ | S48: E16, E35 | T48: 9
A49: E-3 | B49: ESC | C49: Mandatory | D49: Tagging: named attributes, tiered risk types, plural impacted entities | E49: Escalation Tagging | F49: The system shall allow escalation matters to be tagged with controlled metadata, with field dependencies, drawn from the same taxonomies used elsewhere in the platform and controlled by dropdown selection. Named attributes: escalation title, escalation identifier, escalation type, identification date, matter description, tier-1 risk type, tier-2 risk type where applicable, impacted entity, the person who identified the matter, the organisational level of the escalation, and the accountable executive. | G49: All named fields; tier-1 and tier-2 from one tiered Risk Type taxonomy; Escalation Impacted Entity child table; captured on /raise-escalation (options from intake_options, retired values not offered) and shown on /escalation. | H49: a | I49: (a) Portal screen | J49: ESC-2026-00007 (LIMIT_BREACH): impacted Line of Business PCB and Material Entity ME_BANK. | K49: escalation.tests.test_entities.TestEscalationMatter.test_identification_and_escalation_dates_are_separate_fields, …test_forums_and_impacted_entities_are_plural, …test_an_unknown_impacted_entity_kind_is_refused; escalation.tests.test_assignment_and_timing.TestRetiredValuesAreNotOffered (all 1); consilium_core.tests.test_taxonomy.TestActiveOnlySearch (all 6) | L49: Pass | M49: ✅ | N49: Direct test | O49: 13 | P49: Config — Link and child-table fields against Core taxonomies. | S49: E3, E16 | T49: 9
A50: E-4 | B50: ESC | C50: Mandatory | D50: Triggers from approved matrices; High, Medium or Low severity drives routing | E50: Escalation Triggers | F50: The system shall support predefined escalation triggers, including adverse events and risk appetite breaches, as defined in approved escalation matrices. Trigger severity — High, Medium, Low — shall determine routing and escalation pathway. | G50: Escalation Matrix + Escalation Matrix Rule (condition, resulting severity, forums, queue, SLA) on desk; routing.apply_routing on save records the rule; raise_escalation lets the matrix set severity or records a manual override; shown on /escalation. | H50: a | I50: (a) Portal screen | J50: Matrix ENTERPRISE-ESC, 13 rules R05-SYSTEMIC … R99-DEFAULT; ESC-2026-00007 matched R10-APPETITE (High, source Matrix); ESC-2026-00003 Manual Override. | K50: escalation.tests.test_routing.TestRouting (all 12); escalation.tests.test_portal_actions.TestRaise.test_the_matrix_sets_the_severity_when_none_is_chosen, …test_a_chosen_severity_is_recorded_as_an_override | L50: Pass | M50: ✅ | N50: Direct test | O50: 16 | P50: Config + Build — Escalation Matrix and its rule rows; build for the rule-resolution at intake. | S50: E16 | T50: 4
A51: E-5 | B51: ESC | C51: Mandatory | D51: Required fields enforced by type and severity; route submission to others for detail and approvals | E51: Logging and Submission | F51: The system shall enforce required data fields at intake while allowing optional fields to vary by escalation type and severity, and shall support routing an initial submission to further individuals through configurable workflow to gather additional detail and obtain approvals. | G51: Template-driven required fields by type and severity, enforced on save and offered on /raise-escalation (template_requirements). Routing to others: the matrix rule's role or group queue (assignment.apply_assignment), queue notice, Take ownership (assignment.take_ownership); send for second-line review (move_matter_status) and review rounds; risk-acceptance approval request to a named approver. All on /escalation. | H51: a | I51: (a) Portal screen | J51: ESC-2026-00012 waiting in group queue Risk Management Function (R75-PROCESS); ESC-2026-00013 taken from Technology and Operations Leadership; templates ESC-INCIDENT, ESC-REGULATORY, ESC-LIMIT. | K51: escalation.tests.test_templates.TestTemplates (all 8); escalation.tests.test_assignment_and_timing.TestAssignmentByGroup (all 10), TestAssignmentByRole (all 1); escalation.tests.test_portal_actions.TestRaise.test_the_escalation_template_is_enforced, TestStatus (all 4) | L51: Pass | M51: ✅ | N51: Direct test | O51: 27 | P51: Config + Build — conditional mandatory-field metadata driven by the selected template; workflow routing. | S51: E16, E27, E33 | T51: 17
A52: E-6 | B52: ESC | C52: Mandatory | D52: Three templates (escalation, action plan, risk acceptance), shared standard fields, plural forums | E52: Configurable Templates | F52: The system shall allow templates to be configured per escalation matter type, with standardized required fields shared across templates. Three templates are specified: the escalation template (identifier, title, type, identification date, tier-1 risk type, accountable executive, governance forum(s), impacted entities, status, trigger, escalation date); the action plan template (escalation identifier, name, start date, end date, accountable executive, owner, status, governance forum(s)); and the risk acceptance template (escalation identifier, name, external risk acceptance identifier where available, start date, end date, accountable executive, status, governance forum(s), rationale). | G52: Escalation Template in three scopes with a shared field set; Action Plan and Risk Acceptance apply their own template; both added from /escalation (add_action_plan, add_risk_acceptance) or desk. | H52: a | I52: (a) Portal screen | J52: ESC-INCIDENT, AP-INCIDENT, RA-LIMIT; ESC-2026-00001 with ACTP-00001, ACTP-00002 and RACC-00001. | K52: escalation.tests.test_templates.TestTemplates (all 8); escalation.tests.test_entities.TestActionPlan (all 2); escalation.tests.test_portal_actions.TestActionPlans (all 4) | L52: Pass | M52: ✅ | N52: Direct test | O52: 17 | P52: Config + Build — Escalation Template with a field-set child table driving required-field behaviour; Action Plan and Risk Acceptance DocTypes. | S52: E16 | T52: 4
A53: E-7 | B53: ESC | C53: Mandatory | D53: Select forums as the pathway; pull participants (Committee Secretary and others) to notify them | E53: Escalation Pathway Mapping | F53: The system shall allow one or more governance forums to be selected as the escalation pathway, drawn from the forum inventory, and shall pull forum participant details — Committee Secretary and others — in order to notify them. | G53: Escalation Forum Link (active forums only), proposed by the matrix, changed on /escalation (routing.set_pathway; a matrix-routed forum cannot be removed). routing.forum_participants resolves chair, secretary and attesting seats (and live delegates) from Forum Membership as at today; breach and material-entity notices reach them and stamp notified_on; "Who a notice reaches" on /escalation. | H53: a | I53: (a) Portal screen | J53: ESC-2026-00007 pathway FRM-2026-00002 and FRM-2026-00005, notified (R10-APPETITE); ESC-2026-00009 and ESC-2026-00001 notified (R20-MATERIAL). | K53: escalation.tests.test_participants.TestPathwayParticipants (all 5); escalation.tests.test_portal_actions.TestPathway (all 4); escalation.tests.test_routing.TestRouting.test_an_inactive_forum_cannot_be_a_destination | L53: Pass | M53: ✅ | N53: Direct test | O53: 13 | P53: Config + Build — child table of Links to Governance Forum; build for participant resolution through the membership records and the notification fan-out. | Q53: Δ | S53: E9, E17, E29 | T53: 13
A54: E-8 | B54: ESC | C54: Mandatory | D54: Automated workflow: role and group assignment, closure docs, matrix routing, material-entity notice to forum, risk-appetite breach path | E54: Configurable Automated Workflow | F54: The system shall automate logging, review, actioning and resolution of escalation matters, including: assignment of users by role and group; attachment and approval of closure documents; workflows, pathways and roles configurable by matter type and severity; storage and reference of escalation matrices for automated routing; automatic notification of the relevant governance forum when a material-entity impact flag is set; and, where the matter is triggered by a risk appetite breach, the ability to flag the breach and follow the breach workflow. Configuration shall require no custom development. | G54: Assignment by role or group from the matrix rule with Take ownership; closure record with criteria and approval stamp (record_matter_closure, close_matter); matrix routing; material-entity notice to pathway forum participants (notify_material_entity_impact); breach flag and path (R10-APPETITE, breach raises severity). Pathways, roles, queues, service levels and required fields are configuration per type and severity. Missing: the workflow itself is not configurable by type and severity: there is no Workflow on Escalation Matter, and move_matter_status lets the stage's role move between any two open states for every type and severity. | H54: d | I54: (d) Not implemented (whole or mandatory part) | J54: ESC-2026-00007 risk-appetite breach, auto-escalated, breach_count 1; ESC-2026-00009 material-entity impact notified; ESCC-00001 … 00004 closures. | K54: escalation.tests.test_assignment_and_timing.TestAssignmentByGroup (all 10), TestAssignmentByRole (all 1); escalation.tests.test_participants.TestPathwayParticipants.test_material_entity_impact_notifies_them_and_stamps_the_forum; escalation.tests.test_resolution.TestSecondLineChallenge.test_material_entity_impact_notifies; escalation.tests.test_routing.TestRouting (all 12) | L54: Pass (qualified) | M54: ✅ (what exists) | N54: Direct test | O54: 29 | P54: Config + Build — workflow configuration; build for matrix-driven routing and the two conditional notification paths. | Q54: Δ | R54: Class (d), No direct test | S54: E17, E27, E33 | T54: 17
A55: E-9 | B55: ESC | C55: Mandatory | D55: Review and challenge with SLA; approvals; periodic reassessment of risk acceptance; delegation; sensitive restriction; systemic escalation to Head of Enterprise Risk; mandatory response template | E55: Configurable Review and Approval Workflow | F55: The system shall support a structured, role-based review and approval process. Review and challenge: multi-step review by role and severity, including configurable second-line-of-defence challenge with service levels before escalation to accountable executives or governance forums, with review actions, comments and outcomes retained in the audit trail. Approval and accountability: configurable sequential or parallel approvals aligned to type, severity and organisational hierarchy; risk acceptance workflows with documented approvals and periodic reassessment; accountability tracked by role with timestamps and decision records. Pathways and exceptions: configurable pathways aligned to governance forum structures and organisational hierarchy; delegation of routing responsibility where permitted; exception handling; restricted access for sensitive escalations; escalation to the Head of Enterprise Risk for systemic issues. Completion of the escalation response template is mandatory for all escalations, including those tracked in an external system. | G55: Review rounds from /escalation (record_review_round, independent of the accountable people); second-line challenge clock (Time In State on requires_review, scoped {"systemic": 1}) stamped on the round; systemic route (matrix rule on systemic to a higher role and forums); risk-acceptance approval by an independent named approver or a forum motion, with delegation through Authority Delegation; reassessment and expiry reminders (reminders.remind_risk_acceptances, daily); sensitive restriction; response-template gate on closure. Missing: configurable sequential or parallel approvals aligned to type, severity and hierarchy: an acceptance takes one named approver (a second request is refused), and nothing configures an approval chain for escalations. | H55: d | I55: (d) Not implemented (whole or mandatory part) | J55: ESC-2026-00015 systemic (R05-SYSTEMIC, role Head of Risk Governance), review round 1 Challenged against SLAC-00020 (ESC-CHALLENGE-SYSTEMIC, 40 h); RACC-00006 and RACC-00002 Pending Approval; RACC-00004 Approved by decision; RACC-00003 Approved by motion FMOT-2026-00021; RACC-00001 Expired; ADEL-00001 delegation over Risk Acceptance. | K55: escalation.tests.test_assignment_and_timing.TestSystemicRoute (all 2), TestChallengeServiceLevel (all 3); escalation.tests.test_portal_actions.TestReviewRounds (all 5), TestRiskAcceptanceApproval (all 9); escalation.tests.test_resolution.TestRiskAcceptanceApproval (all 5), TestStatesAndClosure.test_closing_without_the_response_template_is_refused; consilium_core.tests.test_reminders.TestEscalationReminders (all 6); consilium_core.tests.test_services.TestApprovals.test_a_delegate_decides_under_a_recorded_delegation | L55: Pass (qualified) | M55: ✅ (what exists) | N55: Direct test | O55: 37 | P55: Config + Build — workflow configuration; build for the challenge service level, the reassessment scheduler and the mandatory-response gate. | R55: Class (d), No direct test | S55: E17, E29, E33 | T55: 8
A56: E-10 | B56: ESC | C56: Mandatory | D56: Enforce closure criteria; auditable closure evidence | E56: Closure Criteria | F56: The system shall enforce defined closure criteria and maintain auditable evidence of closure. | G56: Escalation Closure + Closure Criterion; gate on required criteria and on external reference for a transfer; recorded and closed from /escalation (record_matter_closure, close_matter, confirmation before closing); closer stamped as approver. | H56: a | I56: (a) Portal screen | J56: ESCC-00003 ESC-2026-00006 Transferred Externally (EXTR-00005); ESCC-00004 ESC-2026-00011 Risk Accepted. | K56: escalation.tests.test_resolution.TestStatesAndClosure (all 7); escalation.tests.test_portal_actions.TestClosure (all 5) | L56: Pass | M56: ✅ | N56: Direct test | O56: 14 | P56: Config + Build — Escalation Closure record with evidence attachments; build for the closure gate. | S56: E17, E27 | T56: 16
A57: E-11 | B57: ESC | C57: Mandatory | D57: Generated periodic reports; quarterly tracking; automated reminders; nil-return workflow | E57: Periodic Submission and Tracking | F57: The system shall generate reports directly, replacing manual periodic submissions, and shall support automated quarterly tracking and reporting, including automated reminders and a "no activity" confirmation workflow. | G57: Periodic Submission with the nil-return rule (desk); daily reminders.open_quarter creates the quarter's return once and tells its owner; remind_periodic_returns due and overdue; quarterly analysis and CSV on /reports (analysis.summary, analysis.export, period Quarter). Submission is a desk action by design (trace: CS-5, DK-5, BG). | H57: b | I57: (b) Desk / config / job by design | J57: ESPS-00001 2025-Q4 and ESPS-00002 2026-Q1 Accepted; ESPS-00003 2026-Q2 Submitted; ESPS-00004 2026-Q3 Draft (6 matters). | K57: escalation.tests.test_entities.TestPeriodicSubmission.test_a_period_with_no_matters_must_be_a_nil_return; consilium_core.tests.test_reminders.TestEscalationReminders.test_a_quarter_opening_creates_its_return_once_and_tells_its_owner, …test_quarter_boundaries; escalation.tests.test_analysis.TestAnalysis.test_the_summary_is_exportable_as_csv | L57: Pass | M57: ✅ | N57: Direct test | O57: 7 | P57: Config + Build — Periodic Submission record; scheduled reminder job; build for the nil-return confirmation. | S57: E5, E17, E29 | T57: 12
A58: E-12 | B58: ESC | C58: Mandatory | D58: History; revert | E58: Version Control, Audit History and Accountability | F58: The system shall track changes to escalation matters, maintain complete history, and log user actions with timestamp and attribution, retaining version history. Revert to a previous version shall be available to authorised users. | G58: consilium_core.revision.snapshot on every save (hooks doc_events); unified history (changes, comments, notifications) and a revision list with Revert (reason required, state and handling kept, closed matters refused) on /escalation; evidence-pack ZIP. | H58: a | I58: (a) Portal screen | J58: 30 matter versions on the demo (ESC-2026-00015 has 4, ESC-2026-00007 has 3). | K58: consilium_core.tests.test_revision.TestMatterRevision (all 13); consilium_core.tests.test_core_controls_wave3.TestHistoryAndEvidencePack (all 4); escalation.tests.test_entities.TestModuleShape.test_every_entity_tracks_changes | L58: Pass | M58: ✅ | N58: Direct test | O58: 21 | P58: Native + Build — native version log; revert is a build. | Q58: Δ | S58: E4, E17, E30 | T58: 10
A59: E-13 | B59: ESC | C59: Mandatory | D59: SLA for workflow steps, status durations and total time open | E59: Service Level Tracking | F59: The system shall track service levels for workflow steps, status durations and total time-open, to support performance monitoring and oversight. | G59: Total time open per matrix rule (Core clock, business calendar, daily breach sweep that raises the matter); time in each status rebuilt from the change log and judged against Time In State definitions (timing.get_time_in_state, state_durations), kept live by the sla.on_subject_update hook and an hourly catch-up; warning at the configured percentage; second-line challenge clock. Shown on /escalation and /reports. Time To First Action is supported by sla.py but no definition is configured, so it is not shown. | H59: a | I59: (a) Portal screen | J59: ESC-HIGH, ESC-MEDIUM, ESC-LOW; ESC-STATE-OPEN, -PROGRESS, -REVIEW, -PENDING; SLAC-00011 ESC-2026-00007 breached 2026-07-31; SLAC-00032 and SLAC-00033 time-in-Open breaches on ESC-2026-00008 and 00010 (no severity raise). | K59: escalation.tests.test_assignment_and_timing.TestTimeInStatus (all 5); consilium_core.tests.test_sla_measures.TestTimeInState (all 8), TestWarningsAndBreaches (all 7); escalation.tests.test_resolution.TestServiceLevels (all 5); escalation.tests.test_wave3_escalation.TestOnlyTheResolutionThresholdRaisesAMatter (all 2); escalation.tests.test_regressions.TestBreachIsNotRepeated (all 2) | L59: Pass | M59: ✅ | N59: Direct test | O59: 34 | P59: Build — service-level definitions, a clock that accrues per state, and breach detection. | Q59: Δ | S59: E17, E29 | T59: 7
A60: E-14 | B60: ESC | C60: Mandatory | D60: Statuses including Open, Under Review, Closed — tracked externally | E60: Status Management | F60: The system shall manage escalation lifecycle statuses, including at minimum Open, Under Review and Closed — tracked externally. | G60: Six configured states mapped to semantic flags (state_flag_seed.py, Workflow State Flag); externally-tracked closure needs the external reference; moved and closed on /escalation. | H60: a | I60: (a) Portal screen | J60: Open ESC-2026-00008, 00010, 00012 … 00014; In Progress 00003, 00007; Under Review 00002, 00009, 00015; Pending Review 00004; Closed 00001, 00005, 00011; Closed — Tracked Externally 00006 (EXTR-00005). | K60: escalation.tests.test_resolution.TestStatesAndClosure.test_a_matter_moves_through_its_states, …test_an_externally_tracked_closure_needs_its_external_reference; escalation.tests.test_portal_actions.TestStatus (all 4), TestClosure.test_closing_as_tracked_elsewhere_takes_the_closures_reference; consilium_core.tests.test_state_flags.TestStateFlags (all 7) | L60: Pass | M60: ✅ | N60: Direct test | O60: 17 | P60: Config — workflow states with semantic flags; the external-closure status is a terminal state carrying an external reference. | Q60: Δ | S60: E17 | T60: 5
A61: E-15 | B61: ESC | C61: Mandatory | D61: Reporting and dashboards: status, severity, risk type, forum, executive; trends; export | E61: Reporting and Dashboards | F61: The system shall provide reporting and dashboards for oversight, monitoring and analysis of escalation matters — status, trends and performance — with filtering and aggregation by status, severity, risk type, governance forum and accountable executive; dashboards configurable for real-time and historical views including service-level progress, upcoming actions and recurring or systemic themes; and export for management, audit and regulatory needs. | G61: /reports escalation section: counts and bars by severity, type, level, age, breaches, appetite, review; analysis.summary (volumes, durations, destinations by forum, outcomes by month, quarter or year) with CSV analysis.export; /emerging-risks trends by tier-1 risk type and escalation type; register sortable by accountable executive and risk types, with Export CSV of the matching rows; desk report builder (DK-5) for any other grouping. All permission-filtered. | H61: a | I61: (a) Portal screen | J61: 15 demo matters; /emerging-risks computes 42 series, 7 rising. | K61: escalation.tests.test_analysis.TestAnalysis (all 5); consilium_core.tests.test_ai_features.TestTrends (all 4) | L61: Pass | M61: ✅ | N61: Direct test | O61: 11 | P61: Native + Build — as G-12. | S61: E17, E20 | T61: 9
A62: E-16 | B62: ESC | C62: Mandatory | D62: RBAC by role; flag and restrict sensitive escalations on every path | E62: Role-Based Access Control | F62: The system shall provide role-based access for individuals and delegates, grouping users by role — escalator, accountable executive or governance forum, response owner, second line of defence, risk governance office — with responsibilities associated to each role, and shall flag and restrict access to escalations designated sensitive. | G62: has_permission and permission_query_conditions on the matter and its three child entities; role Sensitive Escalation Access; named people (response owner, accountable executive, raiser, members of its queue) see their own sensitive matter; the register, reports, analysis, assistant and AI features count only visible rows; only a cleared person may raise a sensitive matter. | H62: a | I62: (a) Portal screen | J62: ESC-2026-00003 and ESC-2026-00004 sensitive. | K62: escalation.tests.test_sensitivity.TestSensitiveMatters (all 8), TestNamedPeopleSeeTheirSensitiveMatters (all 4); escalation.tests.test_portal_actions.TestSensitiveMatter (all 3); escalation.tests.test_entities.TestEscalationMatter.test_permissions | L62: Pass | M62: ✅ | N62: Direct test | O62: 19 | P62: Native + Config + Build — native role and permission engine; build for the sensitive-record restriction, which must survive list, report, search and export paths. | Q62: Δ | S62: E2 | T62: 5
A63: E-17 | B63: ESC | C63: Mandatory | D63: Configurable, templated notifications to users and groups | E63: Notifications | F63: The system shall send configurable, templated, automated notifications to users and groups across the escalation lifecycle. | G63: Every notice goes through notification.notify and an admin-editable Notification Template (12 escalation events: breach, material-entity impact, queued, action plan due and overdue, periodic return opened, due and overdue, risk acceptance expiring, expired, reassessment due and overdue); e-mail by SMTP (framework mail queue) or Microsoft Graph (app-only client credentials; token cached; 401 renews the token; 429, 503 and 504 retried per Retry-After), chosen in Admin → Integrations, with hourly retry and record channel fallback; recipients are named people, matrix user groups, queue members and pathway forum participants. Templates edited on desk (DK-7), sent by jobs and hooks (BG). A real mail relay or Graph tenant needs the target environment. | H63: b | I63: (b) Desk / config / job by design | J63: 52 dispatches on Escalation Matter subjects; reminder log shows escalation.action_plan.overdue ×4, due_soon ×1. | K63: consilium_core.tests.test_notification_templates.TestEventApi (all 10), TestTemplateFailures (all 5), TestEmailRetry (all 3), TestSeeding (all 2); consilium_core.tests.test_graph_mail.TestTheWire (all 8), TestTheDispatchRecord (all 7), TestTheSettings (all 5); escalation.tests.test_assignment_and_timing.TestAssignmentByGroup.test_the_queue_is_told_when_the_matter_enters_it; escalation.tests.test_participants.TestPathwayParticipants.test_a_breach_reaches_the_pathway_forums_people | L63: Pass | M63: ✅ | N63: Direct test | O63: 46 | P63: Native + Config + Build — as G-14. | Q63: Δ | S63: E19, E29, E36 | T63: 12
A64: E-18 | B64: ESC | C64: Mandatory | D64: Retention and WORM | E64: Data and Document Retention | F64: The system shall retain data and documents in accordance with the applicable retention policy and requirements, and shall hold documents and data in a write-once, read-many form for the duration of their retention period. | G64: As G-16: retention and legal-hold guards on every save and delete (wildcard doc_events); ESC-MATTER retention class; daily retention.flag_due_for_disposal schedules a disposal for review and flags held records. Gap: execute_disposition and release_hold are reachable only from code (no desk button, no endpoint); no retention assignment exists on the demo, so nothing is under retention. | H64: c | I64: (c) Partly reachable | J64: Retention class ESC-MATTER; 0 retention assignments, 0 legal holds, 0 disposition events. | K64: consilium_core.tests.test_retention.TestRetention (all 14); consilium_core.tests.test_core_controls_wave3.TestScheduledDisposalReview (all 5) | L64: Pass | M64: ✅ | N64: Direct test | O64: 21 | P64: Build — as G-16. | Q64: Δ | R64: Class (c)
A65: E-19 | B65: ESC | C65: Mandatory | D65: Inbound file import creates matters; outbound export with linkage; forum selection; related risk ids | E65: Integration | F65: The system shall allow escalation matters to be created, updated and tracked consistently across risk, governance and issue-management platforms. Inbound: receive data from external systems — issue management, operational risk events, risk appetite monitoring — to create escalation matters with pre-populated data, with field mapping for completeness, consistency and traceability, and validation and handling rules for missing, invalid or incomplete information. Outbound: send escalation data to external systems for downstream tracking, resolution and reporting, with field mapping and maintained linkage, and synchronisation of status and key attributes where applicable. Governance alignment: select governance forums as pathways using authoritative forum data; link to related risk identifiers for end-to-end traceability; apply restricted handling to sensitive escalations. Technical: configurable methods and frequency; formats supported by both ends; identity platform integration for user selection, routing and notification; alignment to enterprise taxonomies with field mapping and handling rules. | G65: Inbound: /imports (CS-11) upload, review, exclude, revalidate, commit against profile IMPP-00002, with escalation.importing.attach_impacted_entities as the module preparer; a re-import of the same key updates. External Reference; related_risk_reference; forum selection in-database. Gap: outbound export (consilium_core.importing.export_records, Export Batch linkage register) has no screen or endpoint; it is reachable only from tests. | H65: c | I65: (c) Partly reachable | J65: IMPB-00001 Validated against IMPP-00002; EXTR-00006 (RISK_REGISTER RAS-CRE-01) on ESC-2026-00007; 0 export batches. | K65: escalation.tests.test_import_export.TestImportPath (all 4); consilium_core.tests.test_imports_portal.TestReview.test_a_module_preparer_runs_before_the_commit, TestUpload (all 5); consilium_core.tests.test_import_pipeline.TestImportPipeline.test_a_second_import_of_the_same_key_updates_rather_than_duplicates, …test_an_export_batch_records_what_left | L65: Pass | M65: ✅ | N65: Direct test | O65: 15 | P65: Build — inbound becomes the manual/file import path; outbound becomes an export with a linkage register; forum selection is an in-database relationship; identity is app-native with pluggable single sign-on. | Q65: Δ | R65: Class (c) | S65: E21, E28 | T65: 7
A66: O-1 | B66: Supplementary | C66: Supplementary | D66: Home page user guide (setup, forum types, templates, authority, escalation) | F66: A home page carrying a user guide: how to set up a governance forum, definitions of each forum type and how to choose between them, templates (charters, meeting materials, reporting requirements), decision-making authority and escalation protocols. | G66: / reads Guide Article (edited on desk), with built-in fallback text. Articles whose category has no card are still rendered. The help assistant on every page also answers from the illustrated guide chapters, citing them (administration chapters for administrators only). Gap: the create-forum wizard's guidance (CS-4 in the O-1 trace) is static page text, not Guide Article. | H66: a | I66: (a) Portal screen | J66: 6 published articles: guide-getting-started, guide-forum-types, guide-templates, guide-decision-authority, guide-escalation-protocol, guide-policy-lifecycle. | K66: consilium_core.tests.test_w3_guides_core.TestGuideArticlesAreFoundWhereTheAssistantPoints (all 2); consilium_core.tests.test_assistant.TestBuiltInAnswers (all 12), TestAdminDocumentation (all 2); consilium_core.tests.test_portal_pages.TestAdministrator.test_every_page_renders_with_its_key_sections | L66: Pass | M66: ✅ | N66: Direct test | O66: 20 | P66: Build — custom home screen with managed guide content. | S66: E31, E35 | T66: 9
A67: O-2 | B67: Supplementary | C67: Supplementary | D67: Interconnectivity flow chart (home and forum page) | F67: A view of governance interconnectivity between committees, councils and oversight bodies, rendered as a flow chart. | G67: Home page forum map (inventory.forum_map: every forum the viewer may read, with links only where both ends are readable). Forum page SVG (inventory.interconnectivity). | H67: a | I67: (a) Portal screen | J67: All 14 forums and 15 links on /. FRM-2026-00005 Executive Risk Committee with two parents and five children on /forum. | K67: governance.tests.test_governance_gaps.TestInventoryReads.test_the_map_draws_what_the_viewer_may_see, TestPages.test_the_pages_render_with_their_new_sections; governance.tests.test_inventory.TestRelationships (all 2) | L67: Pass | M67: ✅ | N67: Direct test | O67: 6 | P67: Build — consumes the Forum Link relationships. Rendered on both the home page and the forum detail page. | S67: E33 | T67: 1
A68: O-3 | B68: Supplementary | C68: Supplementary | D68: Customisable dashboard: activity, compliance status, gaps in coverage | F68: A customisable visual dashboard summarising forum activity, compliance status and gaps in governance coverage. | G68: /reports forum section plus the coverage-gap matrix (risk category by owning group, empty cells highlighted, forums or documents). /governance-gaps lists coverage gaps by rule. Missing: customisation. The viewer cannot choose, arrange or save what the dashboard shows; the only choice is the forums/documents switch on the matrix. The desk workspace ships no Dashboard Chart or Number Card. | H68: d | I68: (d) Not implemented (whole or mandatory part) | J68: As G-12. | K68: consilium_core.tests.test_ai_features.TestGaps.test_forum_policy_regulatory_and_coverage_gaps_are_found; consilium_core.tests.test_portal_pages.TestAdministrator.test_every_page_renders_with_its_key_sections | L68: Pass (qualified) | M68: ✅ (gap rule and page render; the matrix is counted in the browser and not tested) | N68: Direct test | O68: 4 | P68: Build + Native — custom dashboard screen over native chart/number sources. | R68: Class (d), No direct test | S68: E28 | T68: 4
A69: O-4 | B69: Supplementary | C69: Supplementary | D69: Automated notifications | F69: Automated notifications. | G69: Same as G-14. | H69: d | I69: (d) Not implemented (whole or mandatory part) | J69: As G-14. | K69: As G-14. | L69: Pass (qualified) | M69: ✅ (what exists) | N69: Direct test | P69: Already Mandatory under G-14. | R69: Class (d) | S69: E29 | T69: 2
A70: O-5 | B70: Supplementary | C70: Supplementary | D70: Escalation tracking within the forum module | F70: Escalation tracking and resolution within the forum module. | G70: /forum Escalations tab: "Escalations on this forum's pathway" (inventory.forum_escalations), with the forum's role, notified date and decision motion. It reads matters through the permitted list, so sensitive matters are shown only to cleared readers and never counted. Resolution happens on /escalation. | H70: a | I70: (a) Portal screen | J70: FRM-2026-00006 Operational Risk Committee has 8 pathway matters, including sensitive ESC-2026-00003 and ESC-2026-00004 (Decision). | K70: governance.tests.test_governance_gaps.TestForumEscalations (all 3), TestPages.test_the_pages_render_with_their_new_sections | L70: Pass | M70: ✅ | N70: Direct test | O70: 5 | P70: Satisfied by the in-database relationship to Escalation Matter (S-1). | S70: E33 | T70: 1
A71: O-6 | B71: Supplementary | C71: Supplementary | D71: Real-time governance-gap detection and policy-change impact (external AI) | F71: Real-time detection of governance gaps and impact assessment for policy changes. | G71: Rule-based first, no network: ai.gaps.detect (forum, policy, regulatory and coverage gaps; escalation types no rule names) on /governance-gaps; ai.impact.assess (lineage, applicability, regulation, forums, monitoring, violations, escalations, sections touched) in the Impact panel on /policy and /policy-impact. Optional AI commentary through one audited client (ai/client.py, shared with the help assistant) behind ai/guard.py: classification ceiling, sensitive and Restricted never sent, guidance-only tokens by default, analyst roles and hourly limit, every call an AI Service Request; off until an administrator sets endpoint and key in Admin → Integrations (Assistant Settings; request format "OpenAI-compatible API"; write-only key; Test connection); any failure falls back. Computed at page open over readable records. | H71: a | I71: (a) Portal screen | J71: Connected on the demo site to an OpenAI-compatible provider, guidance-only, classification ceiling Internal: 20 AI Service Request rows, all Succeeded (17 help-assistant answers with citations, 3 governance-gap commentaries), each at Internal classification. /governance-gaps finds 75 gaps (28 High); impact of GDOC-00007 reaches 7 lineage records, 2 forums, 1 regulation. | K71: consilium_core.tests.test_ai_features.TestGaps (all 3), TestImpact (all 11), TestGuard (all 4), TestClient (all 3), TestPages (all 1); consilium_core.tests.test_assistant.TestSettings (all 4), TestAIMode (all 8); consilium_core.tests.test_integrations.TestIntegrationsPage (all 14); consilium_core.tests.test_services.TestProvenance (all 4) | L71: Pass (qualified) | M71: ✅ (automated tests use a stub endpoint; the live run is the demo site's request log) | N71: Direct test | O71: 56 | P71: External AI services — an outbound call with recorded provenance. Not a schema item. | R71: No direct test | S71: E22, E36 | T71: 10
A72: O-7 | B72: Supplementary | C72: Supplementary | D72: Regulatory updates, predictive analytics (external AI + regulatory import) | F72: Real-time regulatory updates, predictive analytics for emerging risks and automated governance risk assessment. | G72: /regulatory-updates: recent changes, citing documents and forums, rule-based candidate documents and sections; record_change saves through the Regulatory Requirement controller, whose fan-out tells owners of citing documents and forums (P-6); file import through /imports with profile IMPP-00001 and policy.regulatory_import.prepare_changes, same fan-out; optional AI suggestions recorded and applied only on a person's accept (decide, AI Suggestion Acceptance with version). /emerging-risks: trends (slope, z-score) and leading indicators over escalations, violations, monitoring and SLA breaches. Governance risk scores with configurable weights on /governance-gaps (ai.scoring.assess). Same guard and client as O-6. | H72: a | I72: (a) Portal screen | J72: REQ_OP_RESILIENCE changed 2026-09-18, cited by GDOC-00007, owner notified; 12 requirements; /emerging-risks 7 rising series, 7 indicators; scores for 13 forums and 14 policies. The AI endpoint is connected (see O-6), but no regulatory suggestion has been requested through it on the demo site. The horizon-scanning platform is reached through /horizon-scanning. | K72: consilium_core.tests.test_ai_features.TestRegulatory (all 8), TestTrends (all 4), TestScoring (all 3), TestPages (all 1); consilium_core.tests.test_regulatory_change.TestRegulatoryChangeFanOut (all 6); consilium_core.tests.test_integrations.TestHorizonScanning (all 3) | L72: Pass (qualified) | M72: ✅ (AI suggestions tested against a stub endpoint only) | N72: Direct test | O72: 28 | P72: External AI services plus the manual regulatory-change import path. Not a schema item. | R72: No direct test | S72: E22, E29, E36 | T72: 13

Sheet Governance
A1: ID | B1: Module | C1: Priority | D1: Short title | E1: Baseline title | F1: Requirement (baseline statement) | G1: What satisfies it | H1: Class | I1: Class meaning | J1: Demo data / workflow | K1: Test(s) | L1: Result | M1: Result as measured | N1: Test evidence | O1: Cited test methods (est.) | P1: Planned satisfaction (baseline) | Q1: Δ decision | R1: Gap sections citing it | S1: Epics tracing it | T1: Stories tracing it
A2: G-1 | B2: CGF | C2: Mandatory | D2: Central forum repository, role-based access | E2: Forum Repository | F2: The system shall provide a centralized, searchable repository of every committee and governance forum, holding forum details, charter documents and associated metadata. Access, visibility and permitted actions shall be governed by role-based access control. | G2: Governance Forum with DocPerm rows; /forums register and /forum detail over the permission-checked REST API; www/forum.py throws for a viewer without read access and offers Edit only with write permission. | H2: a | I2: (a) Portal screen | J2: 14 forums, from FRM-2026-00001 Board of Directors down to working groups (FRM-2026-00013). | K2: governance.tests.test_entities.TestGovernanceEntities (all 19); governance.tests.test_inventory.TestSearchAndFilter.test_search_respects_permissions; consilium_core.tests.test_portal_pages.TestReaderWithoutAccess (all 2) | L2: Pass | M2: ✅ | N2: Direct test | O2: 25 | P2: Config — Governance Forum DocType, attachment handling and the permission engine are native; the register screen is a custom Bootstrap table. | S2: E6 | T2: 6
A3: G-2 | B3: CGF | C3: Mandatory | D3: Advanced search and filter | E3: Search and Retrieval | F3: The system shall provide advanced search and filtering of forums by any indexed metadata field. | G3: /forums filters by type, status, cadence, risk category, operating group and standing, plus the four multi-valued dimensions (inventory.inventory_filters, inventory.tagged_forum_names, intersecting). Free-text search over name, code and mandate, also taken from ?q=. The header's global search finds a forum by identifier or name from any page (consilium_core/search.py). Retired taxonomy values are marked, not offered as new. Paged server-side, with Export CSV. | H3: a | I3: (a) Portal screen | J3: /forums?standing=overdue lists FRM-2026-00008 Model Risk Committee (review due 2026-08-14). | K3: governance.tests.test_inventory.TestSearchAndFilter (all 4); governance.tests.test_governance_gaps.TestInventoryReads.test_tagged_filters_intersect, …test_tagged_names_respect_permission, …test_filter_values_include_retired_ones_marked; consilium_core.tests.test_global_search.TestGlobalSearch (all 9) | L3: Pass | M3: ✅ | N3: Direct test | O3: 19 | P3: Config + Build — native list filtering and report views on Desk; a hand-built filter/search/sort/paginate control on the custom Forum Register. | Q3: Δ | S3: E6, E35 | T3: 11
A4: G-3 | B4: CGF | C4: Mandatory | D4: Forum tagging with controlled taxonomies | E4: Forum Tagging | F4: The system shall allow a forum to be tagged with controlled metadata drawn from standard taxonomies, with dependent-field behaviour and dropdown-controlled selection. Minimum attributes: forum identifier, name, type, description, meeting cadence, chair, primary risk category, legal entity, owning organisation (operating group) and owning organisation (line of business). | G4: Link fields plus four multi-select child tables (business unit, risk type, legal entity, jurisdiction). Operating-group and line-of-business validation. Captured in /create-forum and on desk; shown on /forum. Retired values are not offered (taxonomy standard_queries hook). | H4: a | I4: (a) Portal screen | J4: FRM-2026-00007 Technology and Cyber Risk Committee: type MGMT_CTTE, regulatory-required, 2 business units and 3 risk types. | K4: test_entities.TestGovernanceEntities.test_four_dimensions_are_multi_valued_and_two_are_not, …test_the_owning_organisation_must_be_an_operating_group, …test_a_line_of_business_must_sit_under_its_operating_group; consilium_core.tests.test_entities.TestTaxonomies (all 9); consilium_core.tests.test_taxonomy.TestActiveOnlySearch (all 6) | L4: Pass | M4: ✅ | N4: Direct test | O4: 20 | P4: Config — Link fields to Core taxonomy DocTypes plus child multi-select tables. | Q4: Δ | S4: E3, E6 | T4: 11
A5: G-4 | B5: CGF | C5: Mandatory | D5: Forum mapping; regulatory-required with dependent capture | E5: Forum Mapping | F5: The system shall allow a forum to be mapped to related forums (upstream and downstream), to be flagged as regulatory-required with dependent capture of the applicable regulatory requirements. | G5: parent_forum, Forum Link (upstream and downstream), and Forum Regulatory Requirement, required when the flag is set. inventory.interconnectivity is drawn as SVG on /forum (Linkages tab). Links are edited on desk. | H5: a | I5: (a) Portal screen | J5: 15 Forum Link rows. FRM-2026-00005 Executive Risk Committee answers to FRM-2026-00004 and FRM-2026-00002 and has five sub-committees. 7 regulatory-required forums, for example FRM-2026-00010 with 2 requirements. | K5: test_entities.…test_regulatory_detail_becomes_required_when_the_flag_is_set, …test_a_forum_cannot_be_its_own_ancestor, …test_a_link_takes_its_direction_from_the_field_it_sits_in, …test_a_forum_cannot_link_to_itself; test_inventory.TestRelationships (all 2) | L5: Pass | M5: ✅ | N5: Direct test | O5: 6 | P5: Config — self-referencing child table Forum Link; Forum Regulatory Requirement child table gated on a check field. | S5: E6 | T5: 6
A6: G-5 | B6: CGF | C6: Mandatory | D6: Committee formation: intake, 5-criteria evaluation, evidence, exceptions, status | E6: Committee Formation | F6: The system shall support the committee formation process: structured intake, evaluation against defined criteria, capture of approval evidence, exception handling and status tracking. Evaluation criteria: gap in risk or governance coverage; duplication with existing forums; clear escalation and reporting pathways; alignment with the risk management framework, risk taxonomy and policy structure; resource feasibility. Charter drafts must be reviewable by the Risk Governance Office for completeness and appropriateness before approval. Acceptable approval evidence includes email, meeting minutes and signed documents. Disputes and exceptions resolve through the Head of Risk Governance. | G6: Committee Formation Request + Formation Evaluation (5 criteria seeded) + formation.py. /create-forum → /formation-requests → /formation-request covers findings, return and respond, approval steps, exception to the designated authority, charter challenge, approve, reject and withdraw. Approval creates a draft forum. Gap: Charter Approval Evidence rows are captured on desk only (DK-1 is in the trace). | H6: a | I6: (a) Portal screen | J6: One request at each stage: CFR-2026-00006 Draft; 00004 Under Evaluation; 00003 Returned To Originator; 00002 Pending Approval; 00005 Rejected; 00001 Approved → FRM-2026-00014 Data Governance Council, with bypass EXCA-00001. | K6: governance.tests.test_formation (all 27: TestIntake, TestEvaluation, TestReturnToOriginator, TestApprovalRoute, TestExceptionRoute, TestApprovalCreatesTheForum); governance.tests.test_formation_portal (all 35) | L6: Pass | M6: ✅ | N6: Direct test | O6: 64 | P6: Config + Build — Committee Formation Request with a configured multi-state workflow; Forum Evaluation child table; Committee Charter with attached approval evidence. Build: the gating logic that prevents progression. | Q6: Δ | S6: E7 | T6: 6
A7: G-6 | B7: CGF | C7: Mandatory | D7: Admin-configurable workflows, no code | E7: Configurable Automated Workflow | F7: The system shall support administratively configurable automated workflows for establishing, maintaining and disbanding forums, including approvals and escalations, without custom development. | G7: Formation Approval Route (steps, sequence and mode as data); Workflow State Flag (130 rows); Watched Field Set; disbandment trigger scenarios and approver roles are select options. Nothing branches on a state label. All on desk. | H7: b | I7: (b) Desk / config / job by design | J7: "Standard Formation Approval" route (request type Any). CFR-2026-00002 shows the three steps it raised. | K7: test_formation.TestApprovalRoute.test_the_steps_are_configuration, …test_a_route_change_changes_the_steps_without_a_deployment; consilium_core.tests.test_state_flags.TestStateFlags (all 7); governance.tests.test_lifecycle.TestStateFlags (all 3); test_lifecycle.TestWatchedFields (all 5) | L7: Pass | M7: ✅ | N7: Direct test | O7: 19 | P7: Native + Config — the framework's Workflow engine (states, transitions, role gates) is a configuration record, editable by an administrator. | Q7: Δ | S7: E7 | T7: 6
A8: G-7 | B8: CGF | C8: Mandatory | D8: Governance office controls: completeness, overlap check, charter challenge before approval, validate approvals | E8: Risk Governance Office Controls | F8: The system shall prevent progression of a formation request when required information, approvals or evidence are incomplete or inconsistent. It shall validate intake completeness, check the request against the existing forum inventory for overlap or conflict, allow review and challenge of the draft charter before the requester seeks final approval, and validate submitted approvals against the intake record and charter before the forum inventory is updated. | G8: formation.approval_blockers covers: unassessed criteria; completeness confirmation; undecided steps; refused steps not bypassed; and an uncleared charter challenge (charters.uncleared_challenges). The challenge is recorded on /formation-request (charters.record_charter_challenge). An open challenge also blocks a favourable compliance decision (lifecycle.refuse_standing_over_open_challenge). Gap: the charter's approval evidence (in charters.clearance_blockers) is shown on /forum but is not a formation approval blocker. | H8: a | I8: (a) Portal screen | J8: CFR-2026-00002 is held by CHT-2026-00014 "Changes Requested" and by an open Delegating Authority step. CHT-2026-00007 (FRM-2026-00007) "Changes Requested". | K8: test_formation.TestIntake.test_submission_runs_the_overlap_check; TestEvaluation (all 4); governance.tests.test_governance_gaps.TestFormationCharterGate (all 2), TestStandingGate (all 3); governance.tests.test_wave3_governance.TestCharterChallengeOnTheRequest (all 2); governance.tests.test_charters.TestEffectiveChallenge (all 4) | L8: Pass | M8: ✅ | N8: Direct test | O8: 19 | P8: Build — server-side validation on workflow transition; duplicate-detection query against the forum register; completeness gate on the evaluation child table. | S8: E7, E33 | T8: 7
A9: G-8 | B9: CGF | C9: Mandatory | D9: Multi-step, sequential or parallel approval; path by materiality and forum type | E9: Configurable Review and Approval Workflow | F9: The system shall support a multi-step approval process across stakeholders and roles, with sequential or parallel approvals, capturing charter approval. Approval paths may differ by materiality of change and by forum type. | G9: Route steps become Core Approval Decisions. Sequential order is enforced in approvals.record_decision (waiting_on, is_turn). Parallel steps and peers sharing a sequence number do not wait. Role-based steps form a queue. Steps are decided on /formation-request by the assignee, a queue member or a delegate. A bypass needs an Exception Authorisation, waives only its own step, and cannot be made by the step's own holder. Missing: the path cannot differ by forum type or by materiality of change. formation.resolve_route selects only by request_type (Any, Create, Modify, Retire), and Formation Approval Route has no forum-type or materiality field. | H9: d | I9: (d) Not implemented (whole or mandatory part) | J9: CFR-2026-00002: Risk Governance Office Evaluation (seq 1) approved, Sponsor Endorsement (seq 2) approved, Delegating Authority (seq 2) pending. CFR-2026-00001: Sponsor step bypassed under EXCA-00001. | K9: test_formation.TestApprovalRoute (all 5); test_formation_portal.TestApprovalThroughThePortal (all 5); consilium_core.tests.test_core_controls_wave3.TestSequentialApprovals (all 6); governance.tests.test_wave3_governance.TestFormationStepOrder (all 4); governance.tests.test_w3_guides.TestABypassWaivesOnlyItsOwnStep (all 1), TestNobodyBypassesTheirOwnStep (all 2), TestARoleIsAQueue (all 5); consilium_core.tests.test_services.TestApprovals (all 5) | L9: Pass (qualified) | M9: ✅ (not the path-selection clause) | N9: Direct test | O9: 37 | P9: Config + Build — workflow states and role-gated transitions; build for conditional path selection by change materiality. | R9: Class (d), No direct test | S9: E7 | T9: 6
A10: G-9 | B10: CGF | C10: Mandatory | D10: Full history, attributed; archivable prior versions; revert a forum record | E10: Version Control, Audit History and Accountability | F10: The system shall track every change to a forum, maintain complete history, and log every user action with a timestamp and attributed actor. Prior versions shall be archivable and viewable. The system shall additionally allow an authorised user to revert a forum record to a previous version. | G10: A revision.snapshot doc event on Governance Forum writes a version chain. /forum History tab offers a revision history with Revert (revision.history and revision.revert: reason required, governance office only; lifecycle and derived fields are never restored; reverting a watched field sends the forum back for review). Record history (evidence.record_history, now including notifications) and an evidence-pack ZIP with a SHA-256 manifest (evidence.export_pack). | H10: a | I10: (a) Portal screen | J10: VREV-00001: FRM-2026-00010 Asset-Liability Committee reverted to DVER-00109 with a justification. 40 forum versions. | K10: consilium_core.tests.test_revision.TestForumRevision (all 5); governance.tests.test_governance_gaps.TestForumRevisionCard (all 1); consilium_core.tests.test_core_controls_wave3.TestHistoryAndEvidencePack (all 4); consilium_core.tests.test_versioning.TestVersioning (all 9); consilium_core.tests.test_entities.TestEntityStructure.test_governed_entities_keep_their_change_history | L10: Pass | M10: ✅ | N10: Direct test | O10: 25 | P10: Native + Build — field-level version log and comment threads are native; revert is a build. | Q10: Δ | S10: E4, E30 | T10: 6
A11: G-10 | B11: CGF | C11: Mandatory | D11: Periodic reviews; annual Q1 inventory attestation by chairs, secretaries, owners | E11: Forum Maintenance | F11: The system shall support periodic review schedules including self-assessments, charter reviews and monitoring activities. It shall enforce an annual attestation, conducted in the first quarter, requiring Committee Chairs, Committee Secretaries and Forum Owners to review and confirm the accuracy of the forum inventory. | G11: Attestation engine with inventory and dual-review campaign types (reviews.open_inventory_attestation; attesting seats CHAIR, SECRETARY, FORUM_OWNER have can_attest). The office opens campaigns and generates tasks from /attestation-campaigns (reviews.open_forum_campaign, generate_forum_campaign_tasks). Tasks are answered and counter-signed in /tasks. Reminders follow each campaign's schedule (reminders.remind_attestation_campaigns, daily). The annual review is run from the forum (/forum-review#annual-review). The overdue chase goes to owners (reminders.remind_forum_reviews). last_attested_on is stamped. Missing: nothing enforces or schedules the first quarter. No job opens the Q1 campaign or flags a year with none. The screen defaults the due date to today + 45 days and accepts any dates. | H11: d | I11: (d) Not implemented (whole or mandatory part) | J11: ACAM-00002 "Forum inventory attestation 2026": 22 attested, 3 with exceptions, 3 declined, 11 pending. It opened 2026-08-04, due 2026-10-03, so outside Q1. ACAM-00003 dual review; ACAM-00001 (2025) closed. Annual reviews FCR-2026-00015/16/17. | K11: consilium_core.tests.test_attestation.TestAttestation (all 13), TestUnconfiguredRecordsDoNotStopACampaign (all 3); consilium_core.tests.test_inbox.TestInboxAttestation (all 8), TestSecondSignature (all 3), TestCampaignAdministration (all 5); consilium_core.tests.test_w3_guides_core.TestCampaignReminderSchedule (all 4); consilium_core.tests.test_reminders.TestForumReviewReminders (all 1); governance.tests.test_lifecycle.TestAnnualReview (all 4); governance.tests.test_w3_guides.TestAnnualReviewFromTheForum (all 4); test_inventory.TestAttestationStamp (all 3) | L11: Pass (qualified) | M11: ✅ (not the Q1 clause) | N11: Direct test | O11: 54 | P11: Build — the shared attestation campaign/task engine, with a CGF inventory campaign type; scheduled job generates tasks and reminders. | Q11: Δ | R11: Class (d), No direct test | S11: E8, E18, E28 | T11: 13
A12: G-11 | B12: CGF | C12: Mandatory | D12: Configurable disbandment: triggers, approvals, plan artefact | E12: Committee Disbanding | F12: The system shall provide a configurable disbandment workflow covering trigger scenarios (annual inventory review, self-assessment outcome, charter review, completion of mandate), validation of closure approvals from the delegating authority, sponsor, chair and — where applicable — the jurisdictional Chief Risk Officer, and capture of a formal disbandment plan as an uploaded, tracked artefact. | G12: /forum-disband (linked from /forum): lifecycle.raise_disbandment_plan (the governance office; five trigger scenarios; delegating authority, sponsor and chair required, jurisdictional CRO optional); attach_disbandment_file (only a file attached to this plan); record_disbandment_decision (approver or delegate); execute_forum_disbandment (waits for every approval; the forum becomes inactive, never deleted). | H12: a | I12: (a) Portal screen | J12: FDIS-2026-00001: FRM-2026-00012 Outsourcing Oversight Forum disbanded 2026-04-21, successor FRM-2026-00013. FDIS-2026-00002 (FRM-2026-00013) live: delegating authority approved, sponsor and chair pending. Neither demo plan has a plan file attached. | K12: governance.tests.test_governance_gaps.TestDisbandmentPortal (all 8); governance.tests.test_lifecycle.TestDisbandment (all 5); test_entities.…test_a_disbandment_plan_needs_the_approvals_it_requires; test_formation_portal.TestComplianceReviewThroughThePortal.test_a_disbanded_forum_is_not_reviewed_again | L12: Pass | M12: ✅ | N12: Direct test | O12: 17 | P12: Config + Build — terminal workflow state with its own approval path; Disbandment Plan DocType; build for the approval-completeness gate and the retention consequence. | S12: E8 | T12: 5
A13: G-12 | B13: CGF | C13: Mandatory | D13: Reporting and dashboards: status, coverage, compliance, performance; drill-down; export | E13: Reporting and Dashboards | F13: The system shall provide reporting and dashboards for oversight of forums enterprise-wide: status, coverage, compliance and performance metrics; filtering, aggregation and drill-down by forum type, status, legal entity, risk coverage, ownership and review or attestation status; current and historical views including forums in formation, active forums, upcoming reviews, overdue actions and service-level performance; export of reports and artefacts for management, audit and regulatory needs. | G13: /reports: forums awaiting review, overdue, regulatory-required, disbanded; by compliance status and by type; coverage matrix of risk category by owning group, with empty cells highlighted. Every figure links to the filtered /forums. Also /governance-gaps (ai.gaps.detect: coverage, forum, policy and regulatory gaps; ai.scoring.assess); /formation-requests for forums in formation; /attestation-campaigns board for attestation status. Export CSV on /forums exports the matching rows through the permission-checked list (up to 5,000 rows, formula-safe). Gap: no service-level performance for forums or formation (no SLA Definition targets either doctype). | H13: c | I13: (c) Partly reachable | J13: FRM-2026-00007 Non-Compliant; FRM-2026-00013 Pending; FRM-2026-00011 and FRM-2026-00014 Draft; FRM-2026-00012 Disbanded; FRM-2026-00008 overdue. | K13: consilium_core.tests.test_ai_features.TestGaps.test_forum_policy_regulatory_and_coverage_gaps_are_found; consilium_core.tests.test_ai_features.TestPages (all 1); consilium_core.tests.test_portal_pages.TestAdministrator.test_every_page_renders_with_its_key_sections | L13: Pass (qualified) | M13: ✅ (gap rules and page render only; no forum figure is tested) | N13: Direct test | O13: 6 | P13: Native + Build — native report builder, query reports, dashboard charts and export on Desk; custom Bootstrap dashboard screens for the daily-use views. | R13: Class (c), No direct test | S13: E10, E20 | T13: 9
A14: G-13 | B14: CGF | C14: Mandatory | D14: RBAC with delegates; groupings; nomination of delegates | E14: Role-Based Access Control | F14: The system shall provide role-based access for individuals and their delegates (Committee Secretary, Forum Owner, Reviewer, Approver, Viewer, Administrator). It shall support grouping users by role and attribute (line of business, first/second line of defence, legal, compliance, voting versus non-voting). Chairs, sponsors and secretaries shall be able to nominate delegates for administrative tasks. | G14: Roles (Committee Secretary, Forum Owner, Compliance Reviewer, Governance Viewer, Risk Governance Office, Consilium Administrator, Consilium Audit and others). Seat roles carry vote, quorum and attest flags. Authority Delegation with a validity window (delegation.resolve_actor). Seat delegates on Forum Membership. Gap: chairs and sponsors cannot nominate a delegate themselves. Only System Manager and Consilium Administrator may create Authority Delegation. Seat delegates are set on desk by the Committee Secretary or the governance office. | H14: c | I14: (c) Partly reachable | J14: 23 personas. ADEL-00001…00004 (ADEL-00002 expired). FMEM-00031 on FRM-2026-00005 has a standing delegate. | K14: consilium_core.tests.test_delegation.TestDelegation (all 13); consilium_core.tests.test_entities.TestPermissions (all 5); governance.tests.test_membership.TestDelegation (all 3); governance.tests.test_voting.TestDelegatedVoting (all 3); test_w3_guides.TestARoleIsAQueue (all 5) | L14: Pass | M14: ✅ | N14: Direct test | O14: 33 | P14: Native + Config + Build — native role/permission engine and user groups; forum-scoped accountability roles are modelled as membership rows; build for delegation validity windows. | Q14: Δ | R14: Class (c) | S14: E2, E9 | T14: 11
A15: G-14 | B15: CGF | C15: Mandatory | D15: Configurable, templated, automated notifications (approvals, reviews, escalations, meetings, attestation, charter reviews) | E15: Notifications | F15: The system shall send configurable, templated, automated notifications for approvals, reviews, escalations, meeting schedules, annual attestation and charter reviews. | G15: Notification Template per event (49, admin-editable per channel; notification.notify). There is an e-mail adapter over SMTP or Microsoft Graph, falling back to the record channel, with retry. Every caller now raises an event; none sends hard-coded text. Governance events: formation returned, approval requested, exception raised, approved and rejected; forum review recorded, returned for review and disbanded; disbandment approval requested (governance.disbandment.approval_requested, from lifecycle.raise_disbandment); forum review overdue; attestation open and second signature missing; attestation task reminder. Missing: no notification for meeting schedules or charter reviews (no event code, template or caller). | H15: d | I15: (d) Not implemented (whole or mandatory part) | J15: 201 dispatches: 178 EMAIL, 23 RECORD. For example "Formation approval requested" (8), "Compliance review recorded" (34). The 2 "Forum disbandment awaits your approval" dispatches were written by the demo load before that notice was templated. Reminder Log row for governance.forum_review.overdue on FRM-2026-00008. | K15: governance.tests.test_wave3_governance.TestTemplatedNotices (all 3); consilium_core.tests.test_notification_templates.TestSeeding (all 2), TestEventApi (all 10), TestTemplateFailures (all 5), TestEmailRetry (all 3); consilium_core.tests.test_notification.TestNotification (all 6); test_formation.TestReturnToOriginator.test_the_originator_is_notified; test_lifecycle.TestWatchedFields.test_compliance_is_notified_and_a_task_is_raised; governance.tests.test_governance_gaps.TestDisbandmentPortal.test_raising_names_g11s_approvers_and_asks_them | L15: Pass (qualified) | M15: ✅ (what exists; nothing tests the missing meeting and charter notices) | N15: Direct test | O15: 36 | P15: Native + Config + Build — native notification definitions and email queue; build for the pluggable channel abstraction. | Q15: Δ | R15: Class (d), No direct test | S15: E9, E19, E29, E36 | T15: 18
A16: G-15 | B16: CGF | C16: Mandatory | D16: Attach any documents, with version control and audit log; retain all | E16: Document Management | F16: The system shall allow documents to be attached without restriction on type or count — templates, charters and mandates, agendas, meeting minutes and related material — with version control, and shall show an audit log of all activity. All documents and history shall be retained. | G16: Native attachments and activity log. On /forum Documents: start a charter (charters.start_forum_charter) and take a new charter version with a change summary (charters.publish_charter_version, only a file attached to that charter; this reopens the challenge). Minutes are versioned through the desk button "Record minutes" (meetings.record_meeting_minutes). Meeting agenda file. Deletion guarded. | H16: a | I16: (a) Portal screen | J16: 14 charters, 17 charter versions (CHT-2026-00005, CHT-2026-00007 and CHT-2026-00011 have 2 each). 67 meetings, 38 with a minutes version (for example FMTG-2026-00035). | K16: governance.tests.test_governance_gaps.TestCharterPortal (all 9); governance.tests.test_charters.TestCharterVersions (all 2); governance.tests.test_regressions.TestMinutes (all 3) | L16: Pass | M16: ✅ | N16: Direct test | O16: 17 | P16: Native + Build — native attachment handling and activity log; build for the document version chain and its retention linkage. | Q16: Δ | S16: E5, E33 | T16: 6
A17: G-16 | B17: CGF | C17: Mandatory | D17: Retention per policy; WORM for the retention period | E17: Data and Document Retention | F17: The system shall retain data and documents in accordance with the applicable retention policy and requirements, and shall hold documents and data in a write-once, read-many form for the duration of their retention period. | G17: Retention class, assignment and legal hold on desk. guard_modification and guard_deletion on every doctype. Hash-chained Archive Record. The daily retention.flag_due_for_disposal puts past-retention archives up for approved disposition (held when under legal hold) and deletes nothing. Gap: nothing in the application creates an Archive Record. execute_disposition and release_hold have no caller outside tests, so an approved disposal cannot be carried out from any screen. 0 Retention Assignments on the demo site, so no governance record is actually under retention or WORM (retention_lock reads assignments, not the forum's retention_class field). | H17: c | I17: (c) Partly reachable | J17: 5 retention classes (GOV-MINUTES requires WORM). All 14 forums carry retention_class GOV-FORUM. 0 assignments, 0 archives, 0 dispositions. | K17: consilium_core.tests.test_retention.TestRetention (all 14); consilium_core.tests.test_core_controls_wave3.TestScheduledDisposalReview (all 5) | L17: Pass | M17: ✅ | N17: Direct test | O17: 21 | P17: Build — retention classes, retention schedule evaluation, legal holds, immutable archive records and disposition, built in platform. | Q17: Δ | R17: Class (c) | S17: E5 | T17: 5
A18: G-17 | B18: CGF | C18: Mandatory | D18: Governance intake form with minimum fields; office checks completeness | E18: Governance Intake Form | F18: The system shall allow a request to create, modify or retire a forum to be submitted, with configurable content and a configurable workflow. Intake shall capture at minimum: whether the request is to create a new committee as defined by the enterprise governance standard; the rationale; the purpose and scope; the proposed responsibilities; the delegating authority; whether delegating-authority approval has been obtained (not required at submission); the proposed timeline; and the expected date of the first meeting. The Risk Governance Office shall check completeness and appropriateness before the request proceeds. | G18: /create-forum wizard (guidance, required fields, draft save, compliance-review warning) → formation.submit_request; answer to a return via respond_to_returned_request. Completeness is confirmed on /formation-request. Originators without a governance role can open, answer and withdraw their own request. | H18: a | I18: (a) Portal screen | J18: CFR-2026-00006 Payments Innovation Forum (draft); CFR-2026-00003 returned with questions. | K18: test_formation.TestIntake (all 5); test_formation_portal.TestReturnAndRespond (all 4), TestNamedPeople (all 2); test_w3_guides.TestTheOriginatorReadsTheirOwnRequest (all 3) | L18: Pass | M18: ✅ | N18: Direct test | O18: 14 | P18: Config + Build — Committee Formation Request DocType and workflow; custom Create-Forum wizard screen; build for the completeness gate. | S18: E7 | T18: 6
A19: G-18 | B19: CGF | C19: Mandatory | D19: Standardised intake fields (committee-centric) | E19: Intake Form Fields | F19: The system shall define and enforce a standardized, configurable set of intake fields, validated for completeness and aligned to the platform taxonomies, covering identifying, ownership and organisational information: forum name, forum identifier, requester, forum type, jurisdiction, parent forum, child forum(s), owning organisation (operating group), owning organisation (line of business), owning organisation (business unit), and forum sponsor. | G19: Mandatory and validated fields on Committee Formation Request: name, proposed id, requester, type, jurisdiction, parent, child forums, operating group, line of business, business units, sponsor. The fields G-17 adds are also present: new-committee flag, rationale, purpose and scope, responsibilities, delegating authority and its approval, timeline, first meeting. | H19: a | I19: (a) Portal screen | J19: Any submitted request, for example CFR-2026-00002 Operational Resilience Steering Committee. | K19: test_formation.TestIntake.test_required_fields_are_enforced_before_submission, …test_a_modify_request_must_name_its_subject, …test_one_intake_covers_create_modify_and_retire | L19: Pass | M19: ✅ | N19: Direct test | O19: 3 | P19: Config — mandatory-field and validation metadata on the intake DocType. | Q19: Δ | S19: E7 | T19: 6
A20: G-19 | B20: CGF | C20: Mandatory | D20: Forum data reused (documents, escalations, risk appetite); inbound governed; mapped, validated, traceable | E20: Integration Capabilities | F20: The system shall make forum data available for consistent reuse wherever governance context is required — approving forums for governing documents, escalation pathways, risk appetite and risk identification — and shall consume governance-relevant data from elsewhere. Data exchange shall be field-mapped, validated, and subject to defined handling rules for invalid, missing or incomplete data, and shall be traceable for audit. | G20: Reuse inside the database: Governing Document.approving_forum (listed on /forum) and Escalation Forum Link (Escalations tab on /forum). /imports (CS-11) uploads, maps, validates, reviews rows, commits or discards (importing.upload_batch, revalidate_batch, exclude_row, commit_reviewed_batch, discard_batch). Gap: the outbound export file (importing.export_records) has no caller, so no forum data file can be produced for the risk appetite or risk register. No import profile targets governance data (profiles exist for Escalation Matter and Regulatory Requirement only). External Reference rows are entered on desk. | H20: c | I20: (c) Partly reachable | J20: EXTR-00001…00004 on FRM-2026-00005 and FRM-2026-00006. IMPB-00001 (escalation import, Validated). 0 export batches. FRM-2026-00006 approves 5 governing documents. | K20: consilium_core.tests.test_import_pipeline.TestImportPipeline (all 9); consilium_core.tests.test_imports_portal.TestUpload (all 5), TestReview (all 7), TestDiscard (all 1), TestMethods (all 1); escalation.tests.test_import_export.TestImportPath (all 4) | L20: Pass | M20: ✅ | N20: Direct test | O20: 30 | P20: Config + Build — reuse by Policy and Escalation is an in-database relationship; reuse by the risk appetite system and the risk register is an export file; inbound is the manual import path. | Q20: Δ | R20: Class (c) | S20: E6, E21, E28 | T20: 13

Sheet Policy
A1: ID | B1: Module | C1: Priority | D1: Short title | E1: Baseline title | F1: Requirement (baseline statement) | G1: What satisfies it | H1: Class | I1: Class meaning | J1: Demo data / workflow | K1: Test(s) | L1: Result | M1: Result as measured | N1: Test evidence | O1: Cited test methods (est.) | P1: Planned satisfaction (baseline) | Q1: Δ decision | R1: Gap sections citing it | S1: Epics tracing it | T1: Stories tracing it
A2: P-1 | B2: POL | C2: Mandatory | D2: Central repository with RBAC; restricted handling limits view, download, print, share | E2: Policy Repository | F2: The system shall provide a centralized, searchable repository of all governing documents and their metadata, covering at minimum Frameworks, Policies, Standards, Procedures and Supporting Documents. Access, visibility and permitted actions shall be governed by role-based access control. The system shall identify confidential or restricted documents and apply enhanced handling so that view, download, print and share are limited to authorized roles. | G2: Governing Document (5 types; Directive is deliberately not modelled); /policies, /policy and /document-view. policy/handling.py is registered in hooks.py as has_permission and permission_query_conditions on Governing Document and Document Version, plus File.before_insert (guard_file_privacy). Read is narrowed for Confidential and Restricted documents. Print, download and share are refused per flag and rendition on the print view, file fetch, share and e-mail. Loosening the handling is refused to anyone but the policy office, and the refusal is logged. | H2: a | I2: (a) Portal screen | J2: GDOC-00010 Anti-Money Laundering Policy: Confidential, with the three flags off; PPUB-00008 Targeted Groups, view-only. GDOC-00015 Artificial Intelligence Use Standard: Restricted. | K2: policy.tests.test_handling.TestVisibility (all 8), TestActions (all 7), TestHandlingChanges (all 6), TestVersionBody (all 4), TestVersionHooks (all 2), TestViewerPage (all 5); policy.tests.test_repository.TestGoverningDocument.test_confidential_closes_the_three_actions_by_default | L2: Pass | M2: ✅ | N2: Direct test | O2: 35 | P2: Config + Build — Governing Document DocType and permission rules; build for the restricted-handling controls (download/print/share gating), which are not native. | Q2: Δ | S2: E11, E30 | T2: 7
A3: P-2 | B3: POL | C3: Mandatory | D3: Advanced search and filter | E3: Search and Retrieval | F3: The system shall provide advanced search and filtering of governing documents by metadata. | G3: /policies: filters for type, phase, group, risk category, handling, owner and standing, all kept in the URL. Full-text search over title, reference, abstract, body and the current version's text goes through repository.search, which honours permissions and handling. Owner options come from repository.owners. The header's global search finds a document by reference or title from any page, through the same permission and handling rules. | H3: a | I3: (a) Portal screen | J3: /policies?standing=overdue lists GDOC-00003, GDOC-00009 and GDOC-00014, all in force and past next_review_on. | K3: policy.tests.test_wave3.TestSearch (all 4); test_repository.TestGoverningDocument.test_search_filters_and_matches_title_and_content, …test_search_respects_permissions; consilium_core.tests.test_global_search.TestGlobalSearch (all 9) | L3: Pass | M3: ✅ | N3: Direct test | O3: 17 | P3: Config + Build — as G-2. | Q3: Δ | S3: E11, E35 | T3: 10
A4: P-3 | B4: POL | C4: Mandatory | D4: Metadata tagging (named attributes, accountability roles) | E4: Policy Tagging | F4: The system shall support metadata-driven tagging using controlled fields, field dependencies and standardized taxonomies. Metadata shall include at minimum: document identifiers (name, identifier, type); ownership and accountability roles; organisational alignment; risk classification and applicability; lifecycle status and relationships. Named attributes include document name, document identifier, key contact, document type, jurisdiction, parent document, child document(s), primary risk category, legal entity, owning organisation (operating group), owning organisation (line of business), direct document link, training-required flag, attachments, document approver, document liaison, document owner, document delegate (optional), document sponsor, line of defence, material-entity flag and lifecycle phase. | G4: Every named field and child table, including the accountability-roles table. Shown on /policy, captured on the desk (DK-1), and correctable one field at a time on /policy (metadata.correct_metadata, with a reason). Retired taxonomy values are not offered (standard_queries). | H4: a | I4: (a) Portal screen | J4: GDOC-00005 Outsourcing and Third-Party Risk Policy: regulatory-required, parent GDOC-00003, approving forum FRM-2026-00006. | K4: test_repository.TestGoverningDocument.test_creates_with_required_metadata, …test_refuses_creation_without_required_metadata, …test_material_entity_flag_requires_an_entity; policy.tests.test_entities.TestAccountabilityAndReferences (all 3); policy.tests.test_wave3.TestMetadataCorrection (all 3) | L4: Pass | M4: ✅ | N4: Direct test | O4: 11 | P4: Config — Link and child-table fields against Core taxonomies; accountability roles as a child table. | Q4: Δ | S4: E3, E11 | T4: 10
A5: P-4 | B5: POL | C5: Mandatory | D5: Parent, child and addendum lineage; family dashboard | E5: Document Mapping and Parent-Child Lineage | F5: The system shall allow governing documents to be mapped to related governing documents — parent, child and addendum — and shall present document families in a dashboard view. | G5: Document Relationship plus parent_document, with cycles prevented. lineage.lineage_of is drawn on /policy, and a restricted child is not named to a reader who cannot see it. The "Document families" section on /reports (reporting.families) is permission-filtered and exports to CSV. | H5: a | I5: (a) Portal screen | J5: GDOC-00001 ERM Framework → GDOC-00002, 00003, 00006. GDOC-00003 → 00005, 00007, 00012. GDOC-00008 → 00011. GDOC-00013 (retired) → 00014. | K5: test_repository.TestLineage (all 4); policy.tests.test_wave3.TestLineageVisibility (all 1), TestReporting (all 3) | L5: Pass | M5: ✅ | N5: Direct test | O5: 9 | P5: Config + Build — Document Relationship child table; build for the family/lineage visualisation. | S5: E11, E33 | T5: 6
A6: P-5 | B6: POL | C6: Mandatory | D6: Links to risk-programme objects (forums, risks, controls, training, issues) | E6: Mapping to Risk Programmes | F6: The system shall allow governing documents to be linked to other risk programme objects: risk assessments; processes, risks and controls; training; a regulatory-requirement indicator; and related issues. | G6: In the database: approving_forum, shown on /policy and resolved from /forum; the regulatory-required indicator and references; the training-required flag; the violation → escalation link. The Impact panel on /policy (ai/impact.py) walks the forums, regulation, monitoring and violations. Gap: foreign risks, controls, processes and training items are External Reference rows (or Implementation Plan impacted processes and controls) entered on the desk only. /policy does not show them, and no import profile brings them in for documents. | H6: c | I6: (c) Partly reachable | J6: GDOC-00003 approved by FRM-2026-00006. The 6 External Reference rows on the site are all on forums and escalations; none is on a governing document. | K6: consilium_core.tests.test_ai_features.TestImpact.test_the_rule_based_impact_reaches_lineage_regulation_forums_monitoring_and_violations; policy.tests.test_entities.TestImplementationPlan.test_working_groups_and_references_are_multi_valued | L6: Pass (qualified) | M6: ✅ (in-database links; nothing tests external references on a document's page) | N6: Direct test | O6: 4 | P6: Config + Build — in-platform links where the counterpart is a Consilium record (governance forums, escalations); external references held as imported reference records, not live links. | Q6: Δ | R6: Class (c), No direct test | S6: E12 | T6: 6
A7: P-6 | B7: POL | C7: Mandatory | D7: Regulatory-required with dependent capture; keep references current; notify owners on regulatory change | E7: Regulatory Linkage | F7: The system shall allow a governing document to be designated regulatory-required, and when so designated shall require capture of the relevant regulatory detail through dependent fields. It shall maintain linkage from documents to the applicable laws, rules, regulations or standards, keep references and effective dates current, and notify impacted document owners when a tracked regulatory change occurs. | G7: The flag plus Document Regulatory Reference, shown on /policy. A regulatory-change file is imported on /imports through the seeded profile IMPP-00001 (policy/regulatory_import.py, whose prepare_changes makes a blank cell mean "unchanged"). A change can also be recorded on /regulatory-updates. Either way the Regulatory Requirement controller (notify_citing_owners) tells the owners of citing documents and forums through the templated event regulatory.requirement.changed. | H7: a | I7: (a) Portal screen | J7: 12 requirements. The dispatch "Regulatory change: Operational Resilience Guideline…" went by e-mail to the owner of GDOC-00007. IMPP-00001 is seeded, but no regulatory batch has been run on the demo. | K7: consilium_core.tests.test_regulatory_change.TestRegulatoryChangeFanOut (all 6); policy.tests.test_wave3.TestRegulatoryChangeImport (all 2); consilium_core.tests.test_ai_features.TestRegulatory (all 8); test_repository.TestGoverningDocument.test_regulatory_flag_requires_a_reference | L7: Pass | M7: ✅ | N7: Direct test | O7: 20 | P7: Config + Build — dependent Regulatory Reference child table; regulatory-change intake is an imported file, and the impact-notification fan-out is a build. | Q7: Δ | S7: E12, E29 | T7: 9
A8: P-7 | B8: POL | C8: Mandatory | D8: Configurable lifecycle workflows by type and change; SLA per step; approaching or breached alerts | E8: Configurable Automated Workflow | F8: The system shall support administratively configurable automated workflows for every stage of the document lifecycle, varying by document type and type of change, with conditional routing, tracking and reporting of service levels for all lifecycle steps, and alerts for approaching or breached thresholds. Configuration shall require no custom development. | G8: The framework Workflow Governing Document Lifecycle and Document Lifecycle Gate rows are configured on the desk (DK-4). Conditional routing by type, change and risk comes from Approval Route. A new workflow state needs no schema change (derive_phase_from_state and the Workflow State Flag phase column, opt-in per site). Status-driven SLA clocks per lifecycle step (sla.on_subject_update) and the daily and hourly sla.sweep send the warning (warning_threshold_pct) and the breach through templates. Actions are taken on /policy. Note: step SLAs are seeded for Review and Approved only; other phases need an SLA Definition row. | H8: a | I8: (a) Portal screen | J8: POL-STEP-REVIEW is running on GDOC-00005, 00011 and 00015; POL-STEP-APPROVED on GDOC-00006. The intake clocks POL-INTAKE-MAJOR and MINOR are Met on PINT-00001…03 and Running on PINT-00004 and 00008. | K8: policy.tests.test_lifecycle.TestLifecycleConfiguration (all 5), TestApprovalRouting (all 7); policy.tests.test_w3_state_phase.TestDerivedPhase (all 7); consilium_core.tests.test_sla_measures.TestGoverningDocumentSteps (all 1), TestWarningsAndBreaches (all 7); policy.tests.test_intake.TestClassificationDrivesRoutingAndService (all 5) | L8: Pass | M8: ✅ | N8: Direct test | O8: 36 | P8: Native + Config + Build — native workflow engine; build for the service-level definition, clock and breach alerting. | S8: E12, E29 | T8: 9
A9: P-8 | B9: POL | C9: Mandatory | D9: Multi-step approval: parent-owner approval, reminders, exceptions and exemptions, group routing, annual attestation, horizon-scan scheduling | E9: Configurable Review and Approval Workflow | F9: The system shall support a multi-step approval process across stakeholders and roles, sequential or parallel, including: approval by parent-document owners of changes to child documents where required; automated routing, reminders and escalations; real-time approval tracking with timestamps, comments and sign-offs; forms and workflows for exception requests and exemptions; routing of approvals and notifications to user groups; role-based assignment of approval steps; conditional approval paths by document type, change type or risk level; a full audit trail of approval actions; routing of annual attestation notices and deadline reminders; and horizon-scanning notifications — notifying owners when scans are due, tracking completion of manual scans, and triggering downstream workflow after a scan. | G9: These parts are built: route resolution with a parent-owner step (routing.resolved_steps); steps raised, decided (assignee or live delegate) and bypassed only under an exception authorisation, all from /policy; sequential order enforced; steps in /tasks. Gate exceptions are requested by the owner and approved by the policy office. Exemptions are on the desk, with a daily lapse. Document attestation campaigns are opened from /policy (attestation.open_campaign), with reminders on the campaign schedule and answers in /tasks. Horizon scans are recorded from /policy, chased by daily horizon.remind_due, and a triggering scan opens a review cycle. Missing: (1) reminders and escalation for an approval step left pending. No job reads open Approval Decision rows. The lifecycle-phase SLA warns only the document owner, because sla.RESPONSIBLE_FIELDS names no approver. (2) Routing approvals to user groups. A step resolves to one user from a document field or a named user. required_role is stored but is not used as a queue for policy steps, unlike formation. | H9: d | I9: (d) Not implemented (whole or mandatory part) | J9: GDOC-00005 in Review: 1 step approved, 1 pending. GDOC-00006 Model Risk Management Policy: 3 approved decisions. ACAM-00004: 5 attested, 4 pending. PHSC-00002 → PRVC-00001, review triggered. PEXM-00001 authorised exemption. | K9: policy.tests.test_portal_actions.TestApprovalChain (all 15); test_lifecycle.TestApprovalRouting (all 7), TestParentOwnerApproval (all 3); consilium_core.tests.test_core_controls_wave3.TestSequentialApprovals (all 6); policy.tests.test_wave3.TestGateExceptions (all 4), TestAttestationCampaign (all 2); policy.tests.test_horizon.TestScanCadence (all 8), TestScanTriggersReview (all 5); test_entities.TestExemptionLifecycle (all 5); consilium_core.tests.test_w3_guides_core.TestCampaignReminderSchedule (all 4) | L9: Pass (qualified) | M9: ✅ (what exists; nothing tests approval reminders because there are none) | N9: Direct test | O9: 64 | P9: Config + Build — workflow configuration; build for parent-owner approval injection, attestation campaign integration and horizon-scan scheduling. | Q9: Δ | R9: Class (d), No direct test | S9: E12, E14, E18, E27 | T9: 26
